Workbook

Sheet Census
A1: EMPLOYEE_ID | B1: GENDER | C1: DATE_OF_BIRTH | D1: DATE_OF_HIRE | E1: TERMINATION_DATE | F1: JOB_DURATION | G1: OCCUPATION | H1: SALARY | I1: Knowledge of Work | J1: Communication | K1: Teamwork | L1: Leadership | M1: Quality of Work | N1: Evaluation Score | O1: Evaluation Results
A2: 1238911001 | B2: Female | C2: 19112 | D2: 30963 | E2: 36488 | G2: Stocking Associate | H2: 31200 | I2: 3 | J2: 3 | K2: 2 | L2: 1 | M2: 1 | N2: =ROUND(AVERAGE(I2:M2),0) -> 2 | O2: =IF(N2=1,"Below Expectations",IF(N2=2,"Meets Expectations","Exceeds Expectations")) -> Meets Expectations
A3: 1238911002 | B3: Male | C3: 19833 | D3: 36350 | F3: =IF(E3="",DATEDIF(D3,TODAY(),"y")& "Years" &DATEDIF(D3,TODAY(),"ym")& "Months"&DATEDIF(D3,TODAY(),"md") &"Days",DATEDIF(D3,E3,"y")& "Years" &DATEDIF(D3,E3,"ym")& "Months"&DATEDIF(D3,E3,"md") &"Days") -> 26Years10Months4Days | G3: Stocking Associate | H3: 26000 | I3: 1 | J3: 3 | K3: 1 | L3: 1 | M3: 3 | N3: =ROUND(AVERAGE(I3:M3),0) -> 2 | O3: =IF(N3=1,"Below Expectations",IF(N3=2,"Meets Expectations","Exceeds Expectations")) -> Meets Expectations
A4: 1238911003 | B4: Female | C4: 20527 | D4: 33014 | G4: Stocking Associate | H4: 30602 | I4: 2 | J4: 3 | K4: 1 | L4: 1 | M4: 2 | N4: =ROUND(AVERAGE(I4:M4),0) -> 2 | O4: =IF(N4=1,"Below Expectations",IF(N4=2,"Meets Expectations","Exceeds Expectations")) -> Meets Expectations
A5: 1238911004 | B5: Female | C5: 20864 | D5: 36995 | G5: Warehouse Receiving Associate | H5: 29120 | I5: 2 | J5: 3 | K5: 2 | L5: 3 | M5: 1 | N5: =ROUND(AVERAGE(I5:M5),0) -> 2 | O5: =IF(N5=1,"Below Expectations",IF(N5=2,"Meets Expectations","Exceeds Expectations")) -> Meets Expectations
A6: 1238911005 | B6: Female | C6: 21034 | D6: 36006 | G6: Board Member | H6: 75000 | I6: 1 | J6: 2 | K6: 1 | L6: 1 | M6: 2 | N6: =ROUND(AVERAGE(I6:M6),0) -> 1 | O6: =IF(N6=1,"Below Expectations",IF(N6=2,"Meets Expectations","Exceeds Expectations")) -> Below Expectations
A7: 1238911006 | B7: Male | C7: 34706 | D7: 45441 | F7: =IF(E7="",DATEDIF(D7,TODAY(),"y")& "Years" &DATEDIF(D7,TODAY(),"ym")& "Months"&DATEDIF(D7,TODAY(),"md") &"Days",DATEDIF(D7,E7,"y")& "Years" &DATEDIF(D7,E7,"ym")& "Months"&DATEDIF(D7,E7,"md") &"Days") -> 1Years11Months14Days | G7: Customer Service Help Desk | H7: 46280 | I7: 3 | J7: 2 | K7: 3 | L7: 1 | M7: 1 | N7: =ROUND(AVERAGE(I7:M7),0) -> 2 | O7: =IF(N7=1,"Below Expectations",IF(N7=2,"Meets Expectations","Exceeds Expectations")) -> Meets Expectations
A8: 1238911007 | B8: Female | C8: 21223 | D8: 37919 | E8: 45735 | G8: Inventory Associate | H8: 27586 | I8: 3 | J8: 3 | K8: 1 | L8: 1 | M8: 3 | N8: =ROUND(AVERAGE(I8:M8),0) -> 2 | O8: =IF(N8=1,"Below Expectations",IF(N8=2,"Meets Expectations","Exceeds Expectations")) -> Meets Expectations
A9: 1238911008 | B9: Female | C9: 21236 | D9: 39081 | G9: Inventory Supervisor | H9: 67933.775 | I9: 3 | J9: 1 | K9: 2 | L9: 1 | M9: 3 | N9: =ROUND(AVERAGE(I9:M9),0) -> 2 | O9: =IF(N9=1,"Below Expectations",IF(N9=2,"Meets Expectations","Exceeds Expectations")) -> Meets Expectations
A10: 1238911009 | B10: Male | C10: 21283 | D10: 39668 | G10: Marketing Coordinator | H10: 67860 | I10: 3 | J10: 1 | K10: 1 | L10: 3 | M10: 3 | N10: =ROUND(AVERAGE(I10:M10),0) -> 2 | O10: =IF(N10=1,"Below Expectations",IF(N10=2,"Meets Expectations","Exceeds Expectations")) -> Meets Expectations
A11: 1238911010 | B11: Female | C11: 34729 | D11: 42711 | G11: Marketing Coordinator | H11: 67860 | I11: 3 | J11: 2 | K11: 3 | L11: 2 | M11: 2 | N11: =ROUND(AVERAGE(I11:M11),0) -> 2 | O11: =IF(N11=1,"Below Expectations",IF(N11=2,"Meets Expectations","Exceeds Expectations")) -> Meets Expectations
A12: 1238911011 | B12: Female | C12: 34051 | D12: 42958 | E12: 45662 | G12: Warehouse Receiving Associate | H12: 30030 | I12: 1 | J12: 1 | K12: 1 | L12: 2 | M12: 3 | N12: =ROUND(AVERAGE(I12:M12),0) -> 2 | O12: =IF(N12=1,"Below Expectations",IF(N12=2,"Meets Expectations","Exceeds Expectations")) -> Meets Expectations
A13: 1238911012 | B13: Female | C13: 21673 | D13: 38324 | E13: 44487 | G13: Stocking Associate | H13: 27456 | I13: 2 | J13: 3 | K13: 3 | L13: 2 | M13: 2 | N13: =ROUND(AVERAGE(I13:M13),0) -> 2 | O13: =IF(N13=1,"Below Expectations",IF(N13=2,"Meets Expectations","Exceeds Expectations")) -> Meets Expectations
A14: 1238911013 | B14: Female | C14: 35055 | D14: 44296 | G14: Stocking Associate | H14: 32864 | I14: 3 | J14: 2 | K14: 3 | L14: 3 | M14: 1 | N14: =ROUND(AVERAGE(I14:M14),0) -> 2 | O14: =IF(N14=1,"Below Expectations",IF(N14=2,"Meets Expectations","Exceeds Expectations")) -> Meets Expectations
A15: 1238911014 | B15: Female | C15: 21784 | D15: 36400 | G15: Stocking Associate | H15: 32864 | I15: 3 | J15: 2 | K15: 3 | L15: 3 | M15: 3 | N15: =ROUND(AVERAGE(I15:M15),0) -> 3 | O15: =IF(N15=1,"Below Expectations",IF(N15=2,"Meets Expectations","Exceeds Expectations")) -> Exceeds Expectations
A16: 1238911015 | B16: Male | C16: 21798 | D16: 38976 | E16: 41564 | F16: =IF(E16="",DATEDIF(D16,TODAY(),"y")& "Years" &DATEDIF(D16,TODAY(),"ym")& "Months"&DATEDIF(D16,TODAY(),"md") &"Days",DATEDIF(D16,E16,"y")& "Years" &DATEDIF(D16,E16,"ym")& "Months"&DATEDIF(D16,E16,"md") &"Days") -> 7Years1Months1Days | G16: Accountant | H16: 43914 | I16: 3 | J16: 2 | K16: 2 | L16: 2 | M16: 2 | N16: =ROUND(AVERAGE(I16:M16),0) -> 2 | O16: =IF(N16=1,"Below Expectations",IF(N16=2,"Meets Expectations","Exceeds Expectations")) -> Meets Expectations
A17: 1238911016 | B17: Male | C17: 31090 | D17: 41215 | E17: 43065 | F17: =IF(E17="",DATEDIF(D17,TODAY(),"y")& "Years" &DATEDIF(D17,TODAY(),"ym")& "Months"&DATEDIF(D17,TODAY(),"md") &"Days",DATEDIF(D17,E17,"y")& "Years" &DATEDIF(D17,E17,"ym")& "Months"&DATEDIF(D17,E17,"md") &"Days") -> 5Years0Months24Days | G17: Accounting Associate | H17: 43914 | I17: 1 | J17: 3 | K17: 1 | L17: 2 | M17: 2 | N17: =ROUND(AVERAGE(I17:M17),0) -> 2 | O17: =IF(N17=1,"Below Expectations",IF(N17=2,"Meets Expectations","Exceeds Expectations")) -> Meets Expectations
A18: 1238911017 | B18: Female | C18: 21825 | D18: 33014 | E18: 45619 | G18: Stocking Associate | H18: 26520 | I18: 2 | J18: 1 | K18: 3 | L18: 3 | M18: 1 | N18: =ROUND(AVERAGE(I18:M18),0) -> 2 | O18: =IF(N18=1,"Below Expectations",IF(N18=2,"Meets Expectations","Exceeds Expectations")) -> Meets Expectations
A19: 1238911018 | B19: Male | C19: 21846 | D19: 37904 | E19: 44297 | G19: Supervisor | H19: 74679.475 | I19: 3 | J19: 2 | K19: 1 | L19: 3 | M19: 1 | N19: =ROUND(AVERAGE(I19:M19),0) -> 2 | O19: =IF(N19=1,"Below Expectations",IF(N19=2,"Meets Expectations","Exceeds Expectations")) -> Meets Expectations
A20: 1238911019 | B20: Male | C20: 21903 | D20: 33014 | F20: =IF(E20="",DATEDIF(D20,TODAY(),"y")& "Years" &DATEDIF(D20,TODAY(),"ym")& "Months"&DATEDIF(D20,TODAY(),"md") &"Days",DATEDIF(D20,E20,"y")& "Years" &DATEDIF(D20,E20,"ym")& "Months"&DATEDIF(D20,E20,"md") &"Days") -> 35Years11Months22Days | G20: Stocking Associate | H20: 27300 | I20: 2 | J20: 3 | K20: 2 | L20: 2 | M20: 1 | N20: =ROUND(AVERAGE(I20:M20),0) -> 2 | O20: =IF(N20=1,"Below Expectations",IF(N20=2,"Meets Expectations","Exceeds Expectations")) -> Meets Expectations
A21: 1238911020 | B21: Female | C21: 21948 | D21: 38721 | G21: Senior Category Manager | H21: 107723.2 | I21: 2 | J21: 3 | K21: 3 | L21: 2 | M21: 3 | N21: =ROUND(AVERAGE(I21:M21),0) -> 3 | O21: =IF(N21=1,"Below Expectations",IF(N21=2,"Meets Expectations","Exceeds Expectations")) -> Exceeds Expectations
A22: 1238911021 | B22: Female | C22: 21958 | D22: 36183 | E22: 43695 | G22: Stocking Associate | H22: 27571.25 | I22: 2 | J22: 2 | K22: 1 | L22: 1 | M22: 3 | N22: =ROUND(AVERAGE(I22:M22),0) -> 2 | O22: =IF(N22=1,"Below Expectations",IF(N22=2,"Meets Expectations","Exceeds Expectations")) -> Meets Expectations
A23: 1238911022 | B23: Female | C23: 28244 | D23: 39815 | G23: Stocking Associate | H23: 27571.25 | I23: 1 | J23: 2 | K23: 1 | L23: 1 | M23: 3 | N23: =ROUND(AVERAGE(I23:M23),0) -> 2 | O23: =IF(N23=1,"Below Expectations",IF(N23=2,"Meets Expectations","Exceeds Expectations")) -> Meets Expectations
A24: 1238911023 | B24: Female | C24: 32709 | D24: 44571 | G24: Stocking Associate | H24: 30784 | I24: 3 | J24: 3 | K24: 3 | L24: 2 | M24: 3 | N24: =ROUND(AVERAGE(I24:M24),0) -> 3 | O24: =IF(N24=1,"Below Expectations",IF(N24=2,"Meets Expectations","Exceeds Expectations")) -> Exceeds Expectations
A25: 1238911024 | B25: Female | C25: 22118 | D25: 37105 | G25: Stocking Associate | H25: 27300 | I25: 3 | J25: 2 | K25: 2 | L25: 2 | M25: 2 | N25: =ROUND(AVERAGE(I25:M25),0) -> 2 | O25: =IF(N25=1,"Below Expectations",IF(N25=2,"Meets Expectations","Exceeds Expectations")) -> Meets Expectations
A26: 1238911025 | B26: Female | C26: 22138 | D26: 36423 | G26: Inventory Supervisor | H26: 65000 | I26: 2 | J26: 1 | K26: 2 | L26: 3 | M26: 3 | N26: =ROUND(AVERAGE(I26:M26),0) -> 2 | O26: =IF(N26=1,"Below Expectations",IF(N26=2,"Meets Expectations","Exceeds Expectations")) -> Meets Expectations
A27: 1238911026 | B27: Female | C27: 22180 | D27: 37729 | G27: Inventory Retrieving Associate | H27: 28596.975 | I27: 1 | J27: 1 | K27: 3 | L27: 1 | M27: 1 | N27: =ROUND(AVERAGE(I27:M27),0) -> 1 | O27: =IF(N27=1,"Below Expectations",IF(N27=2,"Meets Expectations","Exceeds Expectations")) -> Below Expectations
A28: 1238911027 | B28: Female | C28: 22190 | D28: 40172 | G28: Manager of Operations | H28: 101936.25 | I28: 2 | J28: 2 | K28: 2 | L28: 2 | M28: 2 | N28: =ROUND(AVERAGE(I28:M28),0) -> 2 | O28: =IF(N28=1,"Below Expectations",IF(N28=2,"Meets Expectations","Exceeds Expectations")) -> Meets Expectations
A29: 1238911028 | B29: Female | C29: 22293 | D29: 36294 | G29: Field App Engineer | H29: 93062.5 | I29: 1 | J29: 3 | K29: 3 | L29: 1 | M29: 1 | N29: =ROUND(AVERAGE(I29:M29),0) -> 2 | O29: =IF(N29=1,"Below Expectations",IF(N29=2,"Meets Expectations","Exceeds Expectations")) -> Meets Expectations
A30: 1238911029 | B30: Male | C30: 22295 | D30: 35783 | F30: =IF(E30="",DATEDIF(D30,TODAY(),"y")& "Years" &DATEDIF(D30,TODAY(),"ym")& "Months"&DATEDIF(D30,TODAY(),"md") &"Days",DATEDIF(D30,E30,"y")& "Years" &DATEDIF(D30,E30,"ym")& "Months"&DATEDIF(D30,E30,"md") &"Days") -> 28Years4Months24Days | G30: Stocking Associate | H30: 27404 | I30: 3 | J30: 1 | K30: 3 | L30: 3 | M30: 1 | N30: =ROUND(AVERAGE(I30:M30),0) -> 2 | O30: =IF(N30=1,"Below Expectations",IF(N30=2,"Meets Expectations","Exceeds Expectations")) -> Meets Expectations
A31: 1238911030 | B31: Male | C31: 36769 | D31: 45631 | F31: =IF(E31="",DATEDIF(D31,TODAY(),"y")& "Years" &DATEDIF(D31,TODAY(),"ym")& "Months"&DATEDIF(D31,TODAY(),"md") &"Days",DATEDIF(D31,E31,"y")& "Years" &DATEDIF(D31,E31,"ym")& "Months"&DATEDIF(D31,E31,"md") &"Days") -> 1Years5Months8Days | G31: Stocking Associate | H31: 27404 | I31: 2 | J31: 3 | K31: 2 | L31: 2 | M31: 1 | N31: =ROUND(AVERAGE(I31:M31),0) -> 2 | O31: =IF(N31=1,"Below Expectations",IF(N31=2,"Meets Expectations","Exceeds Expectations")) -> Meets Expectations
A32: 1238911031 | B32: Female | C32: 22323 | D32: 36353 | G32: Senior Copywriter | H32: 82875 | I32: 1 | J32: 1 | K32: 2 | L32: 3 | M32: 1 | N32: =ROUND(AVERAGE(I32:M32),0) -> 2 | O32: =IF(N32=1,"Below Expectations",IF(N32=2,"Meets Expectations","Exceeds Expectations")) -> Meets Expectations
A33: 1238911032 | B33: Male | C33: 36193 | D33: 45285 | F33: =IF(E33="",DATEDIF(D33,TODAY(),"y")& "Years" &DATEDIF(D33,TODAY(),"ym")& "Months"&DATEDIF(D33,TODAY(),"md") &"Days",DATEDIF(D33,E33,"y")& "Years" &DATEDIF(D33,E33,"ym")& "Months"&DATEDIF(D33,E33,"md") &"Days") -> 2Years4Months18Days | G33: Stocking Associate | H33: 27300 | I33: 1 | J33: 3 | K33: 1 | L33: 3 | M33: 3 | N33: =ROUND(AVERAGE(I33:M33),0) -> 2 | O33: =IF(N33=1,"Below Expectations",IF(N33=2,"Meets Expectations","Exceeds Expectations")) -> Meets Expectations
A34: 1238911033 | B34: Male | C34: 22413 | D34: 33014 | E34: 42730 | F34: =IF(E34="",DATEDIF(D34,TODAY(),"y")& "Years" &DATEDIF(D34,TODAY(),"ym")& "Months"&DATEDIF(D34,TODAY(),"md") &"Days",DATEDIF(D34,E34,"y")& "Years" &DATEDIF(D34,E34,"ym")& "Months"&DATEDIF(D34,E34,"md") &"Days") -> 26Years7Months5Days | G34: Stocking Associate | H34: 27300 | I34: 2 | J34: 2 | K34: 3 | L34: 2 | M34: 1 | N34: =ROUND(AVERAGE(I34:M34),0) -> 2 | O34: =IF(N34=1,"Below Expectations",IF(N34=2,"Meets Expectations","Exceeds Expectations")) -> Meets Expectations
A35: 1238911034 | B35: Female | C35: 22414 | D35: 37476 | G35: Inventory Retrieving Associate | H35: 28808 | I35: 2 | J35: 1 | K35: 2 | L35: 1 | M35: 2 | N35: =ROUND(AVERAGE(I35:M35),0) -> 2 | O35: =IF(N35=1,"Below Expectations",IF(N35=2,"Meets Expectations","Exceeds Expectations")) -> Meets Expectations
A36: 1238911035 | B36: Female | C36: 22454 | D36: 39338 | G36: Inventory Supervisor | H36: 60797.1 | I36: 2 | J36: 3 | K36: 3 | L36: 2 | M36: 3 | N36: =ROUND(AVERAGE(I36:M36),0) -> 3 | O36: =IF(N36=1,"Below Expectations",IF(N36=2,"Meets Expectations","Exceeds Expectations")) -> Exceeds Expectations
A37: 1238911036 | B37: Male | C37: 22482 | D37: 39788 | F37: =IF(E37="",DATEDIF(D37,TODAY(),"y")& "Years" &DATEDIF(D37,TODAY(),"ym")& "Months"&DATEDIF(D37,TODAY(),"md") &"Days",DATEDIF(D37,E37,"y")& "Years" &DATEDIF(D37,E37,"ym")& "Months"&DATEDIF(D37,E37,"md") &"Days") -> 17Years5Months7Days | G37: Agent Quality Control Monitoring | H37: 48490 | I37: 2 | J37: 3 | K37: 3 | L37: 2 | M37: 3 | N37: =ROUND(AVERAGE(I37:M37),0) -> 3 | O37: =IF(N37=1,"Below Expectations",IF(N37=2,"Meets Expectations","Exceeds Expectations")) -> Exceeds Expectations
A38: 1238911037 | B38: Male | C38: 22501 | D38: 39906 | F38: =IF(E38="",DATEDIF(D38,TODAY(),"y")& "Years" &DATEDIF(D38,TODAY(),"ym")& "Months"&DATEDIF(D38,TODAY(),"md") &"Days",DATEDIF(D38,E38,"y")& "Years" &DATEDIF(D38,E38,"ym")& "Months"&DATEDIF(D38,E38,"md") &"Days") -> 17Years1Months10Days | G38: Stocking Associate | H38: 28782 | I38: 2 | J38: 2 | K38: 1 | L38: 3 | M38: 1 | N38: =ROUND(AVERAGE(I38:M38),0) -> 2 | O38: =IF(N38=1,"Below Expectations",IF(N38=2,"Meets Expectations","Exceeds Expectations")) -> Meets Expectations
A39: 1238911038 | B39: Female | C39: 24539 | D39: 36294 | G39: Stocking Associate | H39: 28782 | I39: 2 | J39: 3 | K39: 3 | L39: 2 | M39: 2 | N39: =ROUND(AVERAGE(I39:M39),0) -> 2 | O39: =IF(N39=1,"Below Expectations",IF(N39=2,"Meets Expectations","Exceeds Expectations")) -> Meets Expectations
A40: 1238911039 | B40: Female | C40: 22507 | D40: 37779 | G40: Inventory Retrieving Associate | H40: 30446 | I40: 2 | J40: 3 | K40: 2 | L40: 1 | M40: 1 | N40: =ROUND(AVERAGE(I40:M40),0) -> 2 | O40: =IF(N40=1,"Below Expectations",IF(N40=2,"Meets Expectations","Exceeds Expectations")) -> Meets Expectations
A41: 1238911040 | B41: Male | C41: 22513 | D41: 38284 | E41: 45539 | F41: =IF(E41="",DATEDIF(D41,TODAY(),"y")& "Years" &DATEDIF(D41,TODAY(),"ym")& "Months"&DATEDIF(D41,TODAY(),"md") &"Days",DATEDIF(D41,E41,"y")& "Years" &DATEDIF(D41,E41,"ym")& "Months"&DATEDIF(D41,E41,"md") &"Days") -> 19Years10Months11Days | G41: Accountant AP | H41: 48317.5 | I41: 1 | J41: 1 | K41: 2 | L41: 2 | M41: 2 | N41: =ROUND(AVERAGE(I41:M41),0) -> 2 | O41: =IF(N41=1,"Below Expectations",IF(N41=2,"Meets Expectations","Exceeds Expectations")) -> Meets Expectations
A42: 1238911041 | B42: Male | C42: 22555 | D42: 39081 | F42: =IF(E42="",DATEDIF(D42,TODAY(),"y")& "Years" &DATEDIF(D42,TODAY(),"ym")& "Months"&DATEDIF(D42,TODAY(),"md") &"Days",DATEDIF(D42,E42,"y")& "Years" &DATEDIF(D42,E42,"ym")& "Months"&DATEDIF(D42,E42,"md") &"Days") -> 19Years4Months13Days | G42: Inventory Retrieving Associate | H42: 31044 | I42: 3 | J42: 3 | K42: 1 | L42: 1 | M42: 1 | N42: =ROUND(AVERAGE(I42:M42),0) -> 2 | O42: =IF(N42=1,"Below Expectations",IF(N42=2,"Meets Expectations","Exceeds Expectations")) -> Meets Expectations
A43: 1238911042 | B43: Male | C43: 22532 | D43: 39668 | F43: =IF(E43="",DATEDIF(D43,TODAY(),"y")& "Years" &DATEDIF(D43,TODAY(),"ym")& "Months"&DATEDIF(D43,TODAY(),"md") &"Days",DATEDIF(D43,E43,"y")& "Years" &DATEDIF(D43,E43,"ym")& "Months"&DATEDIF(D43,E43,"md") &"Days") -> 17Years9Months5Days | G43: Stocking Associate | H43: 30732 | I43: 3 | J43: 2 | K43: 3 | L43: 2 | M43: 2 | N43: =ROUND(AVERAGE(I43:M43),0) -> 2 | O43: =IF(N43=1,"Below Expectations",IF(N43=2,"Meets Expectations","Exceeds Expectations")) -> Meets Expectations
A44: 1238911043 | B44: Female | C44: 22534 | D44: 33014 | E44: 41666 | G44: Inventory Cycle Associate | H44: 30238 | I44: 1 | J44: 2 | K44: 2 | L44: 1 | M44: 3 | N44: =ROUND(AVERAGE(I44:M44),0) -> 2 | O44: =IF(N44=1,"Below Expectations",IF(N44=2,"Meets Expectations","Exceeds Expectations")) -> Meets Expectations
A45: 1238911044 | B45: Female | C45: 22709 | D45: 36498 | G45: Stocking Associate | H45: 28106 | I45: 1 | J45: 1 | K45: 3 | L45: 3 | M45: 3 | N45: =ROUND(AVERAGE(I45:M45),0) -> 2 | O45: =IF(N45=1,"Below Expectations",IF(N45=2,"Meets Expectations","Exceeds Expectations")) -> Meets Expectations
A46: 1238911045 | B46: Female | C46: 22798 | D46: 36400 | G46: Stocking Associate | H46: 29510 | I46: 1 | J46: 2 | K46: 2 | L46: 3 | M46: 2 | N46: =ROUND(AVERAGE(I46:M46),0) -> 2 | O46: =IF(N46=1,"Below Expectations",IF(N46=2,"Meets Expectations","Exceeds Expectations")) -> Meets Expectations
A47: 1238911046 | B47: Female | C47: 22718 | D47: 38976 | G47: Stocking Associate | H47: 30524 | I47: 3 | J47: 1 | K47: 3 | L47: 2 | M47: 3 | N47: =ROUND(AVERAGE(I47:M47),0) -> 2 | O47: =IF(N47=1,"Below Expectations",IF(N47=2,"Meets Expectations","Exceeds Expectations")) -> Meets Expectations
A48: 1238911047 | B48: Male | C48: 22823 | D48: 39846 | F48: =IF(E48="",DATEDIF(D48,TODAY(),"y")& "Years" &DATEDIF(D48,TODAY(),"ym")& "Months"&DATEDIF(D48,TODAY(),"md") &"Days",DATEDIF(D48,E48,"y")& "Years" &DATEDIF(D48,E48,"ym")& "Months"&DATEDIF(D48,E48,"md") &"Days") -> 17Years3Months11Days | G48: Customer Service Associate | H48: 35139 | I48: 1 | J48: 2 | K48: 1 | L48: 1 | M48: 3 | N48: =ROUND(AVERAGE(I48:M48),0) -> 2 | O48: =IF(N48=1,"Below Expectations",IF(N48=2,"Meets Expectations","Exceeds Expectations")) -> Meets Expectations
A49: 1238911048 | B49: Male | C49: 22858 | D49: 37904 | F49: =IF(E49="",DATEDIF(D49,TODAY(),"y")& "Years" &DATEDIF(D49,TODAY(),"ym")& "Months"&DATEDIF(D49,TODAY(),"md") &"Days",DATEDIF(D49,E49,"y")& "Years" &DATEDIF(D49,E49,"ym")& "Months"&DATEDIF(D49,E49,"md") &"Days") -> 22Years7Months3Days | G49: Shipping Associate | H49: 27300 | I49: 1 | J49: 2 | K49: 1 | L49: 1 | M49: 2 | N49: =ROUND(AVERAGE(I49:M49),0) -> 1 | O49: =IF(N49=1,"Below Expectations",IF(N49=2,"Meets Expectations","Exceeds Expectations")) -> Below Expectations
A50: 1238911049 | B50: Male | C50: 26991 | D50: 38664 | F50: =IF(E50="",DATEDIF(D50,TODAY(),"y")& "Years" &DATEDIF(D50,TODAY(),"ym")& "Months"&DATEDIF(D50,TODAY(),"md") &"Days",DATEDIF(D50,E50,"y")& "Years" &DATEDIF(D50,E50,"ym")& "Months"&DATEDIF(D50,E50,"md") &"Days") -> 20Years6Months5Days | G50: Stocking Associate | H50: 27300 | I50: 2 | J50: 1 | K50: 3 | L50: 1 | M50: 2 | N50: =ROUND(AVERAGE(I50:M50),0) -> 2 | O50: =IF(N50=1,"Below Expectations",IF(N50=2,"Meets Expectations","Exceeds Expectations")) -> Meets Expectations
A51: 1238911050 | B51: Male | C51: 22888 | D51: 40019 | F51: =IF(E51="",DATEDIF(D51,TODAY(),"y")& "Years" &DATEDIF(D51,TODAY(),"ym")& "Months"&DATEDIF(D51,TODAY(),"md") &"Days",DATEDIF(D51,E51,"y")& "Years" &DATEDIF(D51,E51,"ym")& "Months"&DATEDIF(D51,E51,"md") &"Days") -> 16Years9Months18Days | G51: Stocking Associate | H51: 27664 | I51: 2 | J51: 3 | K51: 2 | L51: 1 | M51: 3 | N51: =ROUND(AVERAGE(I51:M51),0) -> 2 | O51: =IF(N51=1,"Below Expectations",IF(N51=2,"Meets Expectations","Exceeds Expectations")) -> Meets Expectations
A52: 1238911051 | B52: Male | C52: 22932 | D52: 38721 | F52: =IF(E52="",DATEDIF(D52,TODAY(),"y")& "Years" &DATEDIF(D52,TODAY(),"ym")& "Months"&DATEDIF(D52,TODAY(),"md") &"Days",DATEDIF(D52,E52,"y")& "Years" &DATEDIF(D52,E52,"ym")& "Months"&DATEDIF(D52,E52,"md") &"Days") -> 20Years4Months9Days | G52: Inventory Retrieving Associate | H52: 29822.5 | I52: 2 | J52: 1 | K52: 3 | L52: 2 | M52: 2 | N52: =ROUND(AVERAGE(I52:M52),0) -> 2 | O52: =IF(N52=1,"Below Expectations",IF(N52=2,"Meets Expectations","Exceeds Expectations")) -> Meets Expectations
A53: 1238911052 | B53: Male | C53: 22997 | D53: 38009 | F53: =IF(E53="",DATEDIF(D53,TODAY(),"y")& "Years" &DATEDIF(D53,TODAY(),"ym")& "Months"&DATEDIF(D53,TODAY(),"md") &"Days",DATEDIF(D53,E53,"y")& "Years" &DATEDIF(D53,E53,"ym")& "Months"&DATEDIF(D53,E53,"md") &"Days") -> 22Years3Months20Days | G53: Customer Service Help Desk | H53: 33800 | I53: 3 | J53: 2 | K53: 3 | L53: 2 | M53: 3 | N53: =ROUND(AVERAGE(I53:M53),0) -> 3 | O53: =IF(N53=1,"Below Expectations",IF(N53=2,"Meets Expectations","Exceeds Expectations")) -> Exceeds Expectations
A54: 1238911053 | B54: Male | C54: 23036 | D54: 36535 | F54: =IF(E54="",DATEDIF(D54,TODAY(),"y")& "Years" &DATEDIF(D54,TODAY(),"ym")& "Months"&DATEDIF(D54,TODAY(),"md") &"Days",DATEDIF(D54,E54,"y")& "Years" &DATEDIF(D54,E54,"ym")& "Months"&DATEDIF(D54,E54,"md") &"Days") -> 26Years4Months3Days | G54: Stocking Associate | H54: 31460 | I54: 3 | J54: 3 | K54: 3 | L54: 1 | M54: 2 | N54: =ROUND(AVERAGE(I54:M54),0) -> 2 | O54: =IF(N54=1,"Below Expectations",IF(N54=2,"Meets Expectations","Exceeds Expectations")) -> Meets Expectations
A55: 1238911054 | B55: Female | C55: 23077 | D55: 37105 | G55: Stocking Associate | H55: 30446 | I55: 3 | J55: 3 | K55: 3 | L55: 2 | M55: 3 | N55: =ROUND(AVERAGE(I55:M55),0) -> 3 | O55: =IF(N55=1,"Below Expectations",IF(N55=2,"Meets Expectations","Exceeds Expectations")) -> Exceeds Expectations
A56: 1238911055 | B56: Female | C56: 22465 | D56: 33014 | E56: 42422 | G56: Stocking Associate | H56: 30446 | I56: 1 | J56: 3 | K56: 2 | L56: 2 | M56: 1 | N56: =ROUND(AVERAGE(I56:M56),0) -> 2 | O56: =IF(N56=1,"Below Expectations",IF(N56=2,"Meets Expectations","Exceeds Expectations")) -> Meets Expectations
A57: 1238911056 | B57: Female | C57: 23089 | D57: 44459 | E57: 45478 | G57: Stocking Associate | H57: 31616 | I57: 3 | J57: 2 | K57: 3 | L57: 2 | M57: 3 | N57: =ROUND(AVERAGE(I57:M57),0) -> 3 | O57: =IF(N57=1,"Below Expectations",IF(N57=2,"Meets Expectations","Exceeds Expectations")) -> Exceeds Expectations
A58: 1238911057 | B58: Male | C58: 23153 | D58: 40172 | F58: =IF(E58="",DATEDIF(D58,TODAY(),"y")& "Years" &DATEDIF(D58,TODAY(),"ym")& "Months"&DATEDIF(D58,TODAY(),"md") &"Days",DATEDIF(D58,E58,"y")& "Years" &DATEDIF(D58,E58,"ym")& "Months"&DATEDIF(D58,E58,"md") &"Days") -> 16Years4Months18Days | G58: Inventory Transfer Associate | H58: 29900 | I58: 3 | J58: 3 | K58: 1 | L58: 3 | M58: 2 | N58: =ROUND(AVERAGE(I58:M58),0) -> 2 | O58: =IF(N58=1,"Below Expectations",IF(N58=2,"Meets Expectations","Exceeds Expectations")) -> Meets Expectations
A59: 1238911058 | B59: Male | C59: 23012 | D59: 37729 | F59: =IF(E59="",DATEDIF(D59,TODAY(),"y")& "Years" &DATEDIF(D59,TODAY(),"ym")& "Months"&DATEDIF(D59,TODAY(),"md") &"Days",DATEDIF(D59,E59,"y")& "Years" &DATEDIF(D59,E59,"ym")& "Months"&DATEDIF(D59,E59,"md") &"Days") -> 23Years0Months25Days | G59: Inventory Retrieving Associate | H59: 27404 | I59: 2 | J59: 1 | K59: 3 | L59: 3 | M59: 2 | N59: =ROUND(AVERAGE(I59:M59),0) -> 2 | O59: =IF(N59=1,"Below Expectations",IF(N59=2,"Meets Expectations","Exceeds Expectations")) -> Meets Expectations
A60: 1238911059 | B60: Female | C60: 23210 | D60: 35783 | G60: Dir Content Operation | H60: 152059.7 | I60: 2 | J60: 2 | K60: 3 | L60: 2 | M60: 2 | N60: =ROUND(AVERAGE(I60:M60),0) -> 2 | O60: =IF(N60=1,"Below Expectations",IF(N60=2,"Meets Expectations","Exceeds Expectations")) -> Meets Expectations
A61: 1238911060 | B61: Female | C61: 24871 | D61: 36353 | E61: 43604 | G61: Warehouse Supervisor | H61: 75337.275 | I61: 3 | J61: 1 | K61: 2 | L61: 1 | M61: 3 | N61: =ROUND(AVERAGE(I61:M61),0) -> 2 | O61: =IF(N61=1,"Below Expectations",IF(N61=2,"Meets Expectations","Exceeds Expectations")) -> Meets Expectations
A62: 1238911061 | B62: Female | C62: 23215 | D62: 40386 | G62: Warehouse Supervisor | H62: 75337.275 | I62: 1 | J62: 1 | K62: 3 | L62: 1 | M62: 1 | N62: =ROUND(AVERAGE(I62:M62),0) -> 1 | O62: =IF(N62=1,"Below Expectations",IF(N62=2,"Meets Expectations","Exceeds Expectations")) -> Below Expectations
A63: 1238911062 | B63: Male | C63: 23237 | D63: 37476 | F63: =IF(E63="",DATEDIF(D63,TODAY(),"y")& "Years" &DATEDIF(D63,TODAY(),"ym")& "Months"&DATEDIF(D63,TODAY(),"md") &"Days",DATEDIF(D63,E63,"y")& "Years" &DATEDIF(D63,E63,"ym")& "Months"&DATEDIF(D63,E63,"md") &"Days") -> 23Years9Months5Days | G63: Stocking Associate | H63: 27300 | I63: 2 | J63: 2 | K63: 3 | L63: 1 | M63: 3 | N63: =ROUND(AVERAGE(I63:M63),0) -> 2 | O63: =IF(N63=1,"Below Expectations",IF(N63=2,"Meets Expectations","Exceeds Expectations")) -> Meets Expectations
A64: 1238911063 | B64: Male | C64: 23041 | D64: 39338 | F64: =IF(E64="",DATEDIF(D64,TODAY(),"y")& "Years" &DATEDIF(D64,TODAY(),"ym")& "Months"&DATEDIF(D64,TODAY(),"md") &"Days",DATEDIF(D64,E64,"y")& "Years" &DATEDIF(D64,E64,"ym")& "Months"&DATEDIF(D64,E64,"md") &"Days") -> 18Years8Months0Days | G64: Stocking Associate | H64: 27300 | I64: 1 | J64: 1 | K64: 1 | L64: 2 | M64: 2 | N64: =ROUND(AVERAGE(I64:M64),0) -> 1 | O64: =IF(N64=1,"Below Expectations",IF(N64=2,"Meets Expectations","Exceeds Expectations")) -> Below Expectations
A65: 1238911064 | B65: Male | C65: 23303 | D65: 40471 | F65: =IF(E65="",DATEDIF(D65,TODAY(),"y")& "Years" &DATEDIF(D65,TODAY(),"ym")& "Months"&DATEDIF(D65,TODAY(),"md") &"Days",DATEDIF(D65,E65,"y")& "Years" &DATEDIF(D65,E65,"ym")& "Months"&DATEDIF(D65,E65,"md") &"Days") -> 15Years6Months23Days | G65: Stocking Associate | H65: 27794 | I65: 2 | J65: 3 | K65: 1 | L65: 1 | M65: 1 | N65: =ROUND(AVERAGE(I65:M65),0) -> 2 | O65: =IF(N65=1,"Below Expectations",IF(N65=2,"Meets Expectations","Exceeds Expectations")) -> Meets Expectations
A66: 1238911065 | B66: Male | C66: 23316 | D66: 39788 | F66: =IF(E66="",DATEDIF(D66,TODAY(),"y")& "Years" &DATEDIF(D66,TODAY(),"ym")& "Months"&DATEDIF(D66,TODAY(),"md") &"Days",DATEDIF(D66,E66,"y")& "Years" &DATEDIF(D66,E66,"ym")& "Months"&DATEDIF(D66,E66,"md") &"Days") -> 17Years5Months7Days | G66: Sorter Associate | H66: 26520 | I66: 2 | J66: 2 | K66: 3 | L66: 1 | M66: 3 | N66: =ROUND(AVERAGE(I66:M66),0) -> 2 | O66: =IF(N66=1,"Below Expectations",IF(N66=2,"Meets Expectations","Exceeds Expectations")) -> Meets Expectations
A67: 1238911066 | B67: Female | C67: 25209 | D67: 42462 | E67: 43743 | G67: Stocking Associate | H67: 27404 | I67: 1 | J67: 2 | K67: 2 | L67: 2 | M67: 1 | N67: =ROUND(AVERAGE(I67:M67),0) -> 2 | O67: =IF(N67=1,"Below Expectations",IF(N67=2,"Meets Expectations","Exceeds Expectations")) -> Meets Expectations
A68: 1238911067 | B68: Male | C68: 23468 | D68: 37779 | F68: =IF(E68="",DATEDIF(D68,TODAY(),"y")& "Years" &DATEDIF(D68,TODAY(),"ym")& "Months"&DATEDIF(D68,TODAY(),"md") &"Days",DATEDIF(D68,E68,"y")& "Years" &DATEDIF(D68,E68,"ym")& "Months"&DATEDIF(D68,E68,"md") &"Days") -> 22Years11Months6Days | G68: Customer Service Associate | H68: 27569.325 | I68: 1 | J68: 1 | K68: 1 | L68: 2 | M68: 1 | N68: =ROUND(AVERAGE(I68:M68),0) -> 1 | O68: =IF(N68=1,"Below Expectations",IF(N68=2,"Meets Expectations","Exceeds Expectations")) -> Below Expectations
A69: 1238911068 | B69: Male | C69: 23493 | D69: 42667 | E69: 43382 | F69: =IF(E69="",DATEDIF(D69,TODAY(),"y")& "Years" &DATEDIF(D69,TODAY(),"ym")& "Months"&DATEDIF(D69,TODAY(),"md") &"Days",DATEDIF(D69,E69,"y")& "Years" &DATEDIF(D69,E69,"ym")& "Months"&DATEDIF(D69,E69,"md") &"Days") -> 1Years11Months15Days | G69: Customer Service Associate | H69: 30706 | I69: 2 | J69: 1 | K69: 3 | L69: 2 | M69: 3 | N69: =ROUND(AVERAGE(I69:M69),0) -> 2 | O69: =IF(N69=1,"Below Expectations",IF(N69=2,"Meets Expectations","Exceeds Expectations")) -> Meets Expectations
A70: 1238911069 | B70: Female | C70: 23563 | D70: 43464 | E70: 44662 | G70: Stocking Associate | H70: 28340 | I70: 3 | J70: 1 | K70: 3 | L70: 1 | M70: 2 | N70: =ROUND(AVERAGE(I70:M70),0) -> 2 | O70: =IF(N70=1,"Below Expectations",IF(N70=2,"Meets Expectations","Exceeds Expectations")) -> Meets Expectations
A71: 1238911070 | B71: Female | C71: 23598 | D71: 39668 | G71: Stocking Associate | H71: 29198 | I71: 2 | J71: 1 | K71: 3 | L71: 1 | M71: 3 | N71: =ROUND(AVERAGE(I71:M71),0) -> 2 | O71: =IF(N71=1,"Below Expectations",IF(N71=2,"Meets Expectations","Exceeds Expectations")) -> Meets Expectations
A72: 1238911071 | B72: Male | C72: 23621 | D72: 37114 | F72: =IF(E72="",DATEDIF(D72,TODAY(),"y")& "Years" &DATEDIF(D72,TODAY(),"ym")& "Months"&DATEDIF(D72,TODAY(),"md") &"Days",DATEDIF(D72,E72,"y")& "Years" &DATEDIF(D72,E72,"ym")& "Months"&DATEDIF(D72,E72,"md") &"Days") -> 24Years9Months2Days | G72: Stocking Associate | H72: 26650 | I72: 3 | J72: 1 | K72: 3 | L72: 2 | M72: 1 | N72: =ROUND(AVERAGE(I72:M72),0) -> 2 | O72: =IF(N72=1,"Below Expectations",IF(N72=2,"Meets Expectations","Exceeds Expectations")) -> Meets Expectations
A73: 1238911072 | B73: Male | C73: 23647 | D73: 36498 | F73: =IF(E73="",DATEDIF(D73,TODAY(),"y")& "Years" &DATEDIF(D73,TODAY(),"ym")& "Months"&DATEDIF(D73,TODAY(),"md") &"Days",DATEDIF(D73,E73,"y")& "Years" &DATEDIF(D73,E73,"ym")& "Months"&DATEDIF(D73,E73,"md") &"Days") -> 26Years5Months9Days | G73: Inventory Retrieving Associate | H73: 32266 | I73: 2 | J73: 3 | K73: 1 | L73: 3 | M73: 3 | N73: =ROUND(AVERAGE(I73:M73),0) -> 2 | O73: =IF(N73=1,"Below Expectations",IF(N73=2,"Meets Expectations","Exceeds Expectations")) -> Meets Expectations
A74: 1238911073 | B74: Male | C74: 23680 | D74: 44455 | E74: 45171 | F74: =IF(E74="",DATEDIF(D74,TODAY(),"y")& "Years" &DATEDIF(D74,TODAY(),"ym")& "Months"&DATEDIF(D74,TODAY(),"md") &"Days",DATEDIF(D74,E74,"y")& "Years" &DATEDIF(D74,E74,"ym")& "Months"&DATEDIF(D74,E74,"md") &"Days") -> 1Years11Months17Days | G74: Inventory Retrieving Associate | H74: 32266 | I74: 3 | J74: 2 | K74: 3 | L74: 2 | M74: 2 | N74: =ROUND(AVERAGE(I74:M74),0) -> 2 | O74: =IF(N74=1,"Below Expectations",IF(N74=2,"Meets Expectations","Exceeds Expectations")) -> Meets Expectations
A75: 1238911074 | B75: Female | C75: 23659 | D75: 36400 | G75: Stocking Associate | H75: 27300 | I75: 1 | J75: 2 | K75: 1 | L75: 2 | M75: 2 | N75: =ROUND(AVERAGE(I75:M75),0) -> 2 | O75: =IF(N75=1,"Below Expectations",IF(N75=2,"Meets Expectations","Exceeds Expectations")) -> Meets Expectations
A76: 1238911075 | B76: Female | C76: 23715 | D76: 39846 | G76: Sr. VP Sales & Marketing | H76: 425199.78 | I76: 3 | J76: 2 | K76: 3 | L76: 3 | M76: 3 | N76: =ROUND(AVERAGE(I76:M76),0) -> 3 | O76: =IF(N76=1,"Below Expectations",IF(N76=2,"Meets Expectations","Exceeds Expectations")) -> Exceeds Expectations
A77: 1238911076 | B77: Male | C77: 23719 | D77: 37904 | F77: =IF(E77="",DATEDIF(D77,TODAY(),"y")& "Years" &DATEDIF(D77,TODAY(),"ym")& "Months"&DATEDIF(D77,TODAY(),"md") &"Days",DATEDIF(D77,E77,"y")& "Years" &DATEDIF(D77,E77,"ym")& "Months"&DATEDIF(D77,E77,"md") &"Days") -> 22Years7Months3Days | G77: Stocking Associate | H77: 27300 | I77: 2 | J77: 3 | K77: 1 | L77: 1 | M77: 1 | N77: =ROUND(AVERAGE(I77:M77),0) -> 2 | O77: =IF(N77=1,"Below Expectations",IF(N77=2,"Meets Expectations","Exceeds Expectations")) -> Meets Expectations
A78: 1238911077 | B78: Male | C78: 23732 | D78: 40019 | F78: =IF(E78="",DATEDIF(D78,TODAY(),"y")& "Years" &DATEDIF(D78,TODAY(),"ym")& "Months"&DATEDIF(D78,TODAY(),"md") &"Days",DATEDIF(D78,E78,"y")& "Years" &DATEDIF(D78,E78,"ym")& "Months"&DATEDIF(D78,E78,"md") &"Days") -> 16Years9Months18Days | G78: Stocking Associate | H78: 27300 | I78: 1 | J78: 3 | K78: 1 | L78: 3 | M78: 2 | N78: =ROUND(AVERAGE(I78:M78),0) -> 2 | O78: =IF(N78=1,"Below Expectations",IF(N78=2,"Meets Expectations","Exceeds Expectations")) -> Meets Expectations
A79: 1238911078 | B79: Male | C79: 23876 | D79: 38009 | E79: 45201 | G79: Manager of Operations | H79: 77809.225 | I79: 3 | J79: 3 | K79: 2 | L79: 1 | M79: 3 | N79: =ROUND(AVERAGE(I79:M79),0) -> 2 | O79: =IF(N79=1,"Below Expectations",IF(N79=2,"Meets Expectations","Exceeds Expectations")) -> Meets Expectations
A80: 1238911079 | B80: Female | C80: 23930 | D80: 43840 | E80: 45169 | G80: Stocking Associate | H80: 27300 | I80: 3 | J80: 3 | K80: 3 | L80: 3 | M80: 1 | N80: =ROUND(AVERAGE(I80:M80),0) -> 3 | O80: =IF(N80=1,"Below Expectations",IF(N80=2,"Meets Expectations","Exceeds Expectations")) -> Exceeds Expectations
A81: 1238911080 | B81: Male | C81: 24076 | D81: 37105 | E81: 42146 | G81: Warehouse Supervisor | H81: 59097.675 | I81: 1 | J81: 1 | K81: 3 | L81: 1 | M81: 2 | N81: =ROUND(AVERAGE(I81:M81),0) -> 2 | O81: =IF(N81=1,"Below Expectations",IF(N81=2,"Meets Expectations","Exceeds Expectations")) -> Meets Expectations
A82: 1238911081 | B82: Female | C82: 23832 | D82: 36423 | G82: Supervisor | H82: 59097.675 | I82: 2 | J82: 2 | K82: 1 | L82: 2 | M82: 1 | N82: =ROUND(AVERAGE(I82:M82),0) -> 2 | O82: =IF(N82=1,"Below Expectations",IF(N82=2,"Meets Expectations","Exceeds Expectations")) -> Meets Expectations
A83: 1238911082 | B83: Female | C83: 23953 | D83: 37729 | G83: Stocking Associate | H83: 31616 | I83: 3 | J83: 2 | K83: 3 | L83: 2 | M83: 2 | N83: =ROUND(AVERAGE(I83:M83),0) -> 2 | O83: =IF(N83=1,"Below Expectations",IF(N83=2,"Meets Expectations","Exceeds Expectations")) -> Meets Expectations
A84: 1238911083 | B84: Male | C84: 24037 | D84: 40172 | F84: =IF(E84="",DATEDIF(D84,TODAY(),"y")& "Years" &DATEDIF(D84,TODAY(),"ym")& "Months"&DATEDIF(D84,TODAY(),"md") &"Days",DATEDIF(D84,E84,"y")& "Years" &DATEDIF(D84,E84,"ym")& "Months"&DATEDIF(D84,E84,"md") &"Days") -> 16Years4Months18Days | G84: Stocking Associate | H84: 28782 | I84: 1 | J84: 2 | K84: 2 | L84: 3 | M84: 2 | N84: =ROUND(AVERAGE(I84:M84),0) -> 2 | O84: =IF(N84=1,"Below Expectations",IF(N84=2,"Meets Expectations","Exceeds Expectations")) -> Meets Expectations
A85: 1238911084 | B85: Female | C85: 24044 | D85: 38120 | G85: Chairman Holding | H85: 281250 | I85: 3 | J85: 2 | K85: 2 | L85: 3 | M85: 3 | N85: =ROUND(AVERAGE(I85:M85),0) -> 3 | O85: =IF(N85=1,"Below Expectations",IF(N85=2,"Meets Expectations","Exceeds Expectations")) -> Exceeds Expectations
A86: 1238911085 | B86: Male | C86: 24045 | D86: 35783 | F86: =IF(E86="",DATEDIF(D86,TODAY(),"y")& "Years" &DATEDIF(D86,TODAY(),"ym")& "Months"&DATEDIF(D86,TODAY(),"md") &"Days",DATEDIF(D86,E86,"y")& "Years" &DATEDIF(D86,E86,"ym")& "Months"&DATEDIF(D86,E86,"md") &"Days") -> 28Years4Months24Days | G86: Stocking Associate | H86: 26520 | I86: 2 | J86: 3 | K86: 2 | L86: 1 | M86: 2 | N86: =ROUND(AVERAGE(I86:M86),0) -> 2 | O86: =IF(N86=1,"Below Expectations",IF(N86=2,"Meets Expectations","Exceeds Expectations")) -> Meets Expectations
A87: 1238911086 | B87: Female | C87: 24072 | D87: 36353 | G87: Stocking Associate | H87: 28366 | I87: 3 | J87: 2 | K87: 3 | L87: 1 | M87: 2 | N87: =ROUND(AVERAGE(I87:M87),0) -> 2 | O87: =IF(N87=1,"Below Expectations",IF(N87=2,"Meets Expectations","Exceeds Expectations")) -> Meets Expectations
A88: 1238911087 | B88: Male | C88: 24086 | D88: 40386 | F88: =IF(E88="",DATEDIF(D88,TODAY(),"y")& "Years" &DATEDIF(D88,TODAY(),"ym")& "Months"&DATEDIF(D88,TODAY(),"md") &"Days",DATEDIF(D88,E88,"y")& "Years" &DATEDIF(D88,E88,"ym")& "Months"&DATEDIF(D88,E88,"md") &"Days") -> 15Years9Months16Days | G88: Stocking Associate | H88: 28210 | I88: 1 | J88: 2 | K88: 2 | L88: 1 | M88: 1 | N88: =ROUND(AVERAGE(I88:M88),0) -> 1 | O88: =IF(N88=1,"Below Expectations",IF(N88=2,"Meets Expectations","Exceeds Expectations")) -> Below Expectations
A89: 1238911088 | B89: Male | C89: 24112 | D89: 43320 | E89: 44125 | F89: =IF(E89="",DATEDIF(D89,TODAY(),"y")& "Years" &DATEDIF(D89,TODAY(),"ym")& "Months"&DATEDIF(D89,TODAY(),"md") &"Days",DATEDIF(D89,E89,"y")& "Years" &DATEDIF(D89,E89,"ym")& "Months"&DATEDIF(D89,E89,"md") &"Days") -> 2Years2Months13Days | G89: Inventory Retrieving Associate | H89: 27586 | I89: 3 | J89: 1 | K89: 2 | L89: 2 | M89: 2 | N89: =ROUND(AVERAGE(I89:M89),0) -> 2 | O89: =IF(N89=1,"Below Expectations",IF(N89=2,"Meets Expectations","Exceeds Expectations")) -> Meets Expectations
A90: 1238911089 | B90: Female | C90: 24441 | D90: 39338 | G90: Repair Technician | H90: 39810 | I90: 2 | J90: 3 | K90: 1 | L90: 1 | M90: 3 | N90: =ROUND(AVERAGE(I90:M90),0) -> 2 | O90: =IF(N90=1,"Below Expectations",IF(N90=2,"Meets Expectations","Exceeds Expectations")) -> Meets Expectations
A91: 1238911090 | B91: Male | C91: 24134 | D91: 40471 | F91: =IF(E91="",DATEDIF(D91,TODAY(),"y")& "Years" &DATEDIF(D91,TODAY(),"ym")& "Months"&DATEDIF(D91,TODAY(),"md") &"Days",DATEDIF(D91,E91,"y")& "Years" &DATEDIF(D91,E91,"ym")& "Months"&DATEDIF(D91,E91,"md") &"Days") -> 15Years6Months23Days | G91: Stocking Associate | H91: 27300 | I91: 2 | J91: 3 | K91: 1 | L91: 1 | M91: 3 | N91: =ROUND(AVERAGE(I91:M91),0) -> 2 | O91: =IF(N91=1,"Below Expectations",IF(N91=2,"Meets Expectations","Exceeds Expectations")) -> Meets Expectations
A92: 1238911091 | B92: Male | C92: 24175 | D92: 39788 | E92: 42067 | F92: =IF(E92="",DATEDIF(D92,TODAY(),"y")& "Years" &DATEDIF(D92,TODAY(),"ym")& "Months"&DATEDIF(D92,TODAY(),"md") &"Days",DATEDIF(D92,E92,"y")& "Years" &DATEDIF(D92,E92,"ym")& "Months"&DATEDIF(D92,E92,"md") &"Days") -> 6Years2Months26Days | G92: Clerk Accounting AP | H92: 30673.75 | I92: 1 | J92: 1 | K92: 1 | L92: 1 | M92: 2 | N92: =ROUND(AVERAGE(I92:M92),0) -> 1 | O92: =IF(N92=1,"Below Expectations",IF(N92=2,"Meets Expectations","Exceeds Expectations")) -> Below Expectations
A93: 1238911092 | B93: Female | C93: 24460 | D93: 44289 | E93: 45467 | G93: Stocking Associate | H93: 31460 | I93: 3 | J93: 3 | K93: 3 | L93: 1 | M93: 1 | N93: =ROUND(AVERAGE(I93:M93),0) -> 2 | O93: =IF(N93=1,"Below Expectations",IF(N93=2,"Meets Expectations","Exceeds Expectations")) -> Meets Expectations
A94: 1238911093 | B94: Female | C94: 24186 | D94: 37779 | G94: Sr Mgr Project | H94: 87884.5 | I94: 2 | J94: 2 | K94: 2 | L94: 2 | M94: 2 | N94: =ROUND(AVERAGE(I94:M94),0) -> 2 | O94: =IF(N94=1,"Below Expectations",IF(N94=2,"Meets Expectations","Exceeds Expectations")) -> Meets Expectations
A95: 1238911094 | B95: Female | C95: 24196 | D95: 38284 | G95: Warehouse Associate | H95: 28392 | I95: 3 | J95: 1 | K95: 3 | L95: 3 | M95: 1 | N95: =ROUND(AVERAGE(I95:M95),0) -> 2 | O95: =IF(N95=1,"Below Expectations",IF(N95=2,"Meets Expectations","Exceeds Expectations")) -> Meets Expectations
A96: 1238911095 | B96: Female | C96: 34858 | D96: 43829 | G96: Warehouse Associate | H96: 28392 | I96: 2 | J96: 3 | K96: 1 | L96: 3 | M96: 1 | N96: =ROUND(AVERAGE(I96:M96),0) -> 2 | O96: =IF(N96=1,"Below Expectations",IF(N96=2,"Meets Expectations","Exceeds Expectations")) -> Meets Expectations
A97: 1238911096 | B97: Female | C97: 24214 | D97: 39668 | G97: Customer Service Representative | H97: 30053.75 | I97: 1 | J97: 1 | K97: 2 | L97: 1 | M97: 2 | N97: =ROUND(AVERAGE(I97:M97),0) -> 1 | O97: =IF(N97=1,"Below Expectations",IF(N97=2,"Meets Expectations","Exceeds Expectations")) -> Below Expectations
A98: 1238911097 | B98: Male | C98: 24298 | D98: 37114 | F98: =IF(E98="",DATEDIF(D98,TODAY(),"y")& "Years" &DATEDIF(D98,TODAY(),"ym")& "Months"&DATEDIF(D98,TODAY(),"md") &"Days",DATEDIF(D98,E98,"y")& "Years" &DATEDIF(D98,E98,"ym")& "Months"&DATEDIF(D98,E98,"md") &"Days") -> 24Years9Months2Days | G98: Customer Service Representative | H98: 30053.75 | I98: 3 | J98: 2 | K98: 3 | L98: 1 | M98: 3 | N98: =ROUND(AVERAGE(I98:M98),0) -> 2 | O98: =IF(N98=1,"Below Expectations",IF(N98=2,"Meets Expectations","Exceeds Expectations")) -> Meets Expectations
A99: 1238911098 | B99: Female | C99: 24226 | D99: 36498 | G99: Technician IT Warehouse | H99: 58318 | I99: 1 | J99: 2 | K99: 2 | L99: 1 | M99: 1 | N99: =ROUND(AVERAGE(I99:M99),0) -> 1 | O99: =IF(N99=1,"Below Expectations",IF(N99=2,"Meets Expectations","Exceeds Expectations")) -> Below Expectations
A100: 1238911099 | B100: Female | C100: 24421 | D100: 36400 | G100: Stocking Associate | H100: 35516 | I100: 3 | J100: 3 | K100: 3 | L100: 1 | M100: 2 | N100: =ROUND(AVERAGE(I100:M100),0) -> 2 | O100: =IF(N100=1,"Below Expectations",IF(N100=2,"Meets Expectations","Exceeds Expectations")) -> Meets Expectations
...

Sheet Female_Employees
A1: 1238911001 | B1: Female | C1: 19112 | D1: 30963 | E1: 36488 | F1: Stocking Associate | G1: 31200 | H1: 3 | I1: 3 | J1: 2 | K1: 1 | L1: 1
A2: 1238911003 | B2: Female | C2: 20527 | D2: 33014 | F2: Stocking Associate | G2: 30602 | H2: 2 | I2: 3 | J2: 1 | K2: 1 | L2: 2
A3: 1238911004 | B3: Female | C3: 20864 | D3: 36995 | F3: Warehouse Receiving Associate | G3: 29120 | H3: 2 | I3: 3 | J3: 2 | K3: 3 | L3: 1
A4: 1238911005 | B4: Female | C4: 21034 | D4: 36006 | F4: Board Member | G4: 75000 | H4: 1 | I4: 2 | J4: 1 | K4: 1 | L4: 2
A5: 1238911007 | B5: Female | C5: 21223 | D5: 37919 | E5: 45735 | F5: Inventory Associate | G5: 27586 | H5: 3 | I5: 3 | J5: 1 | K5: 1 | L5: 3
A6: 1238911008 | B6: Female | C6: 21236 | D6: 39081 | F6: Inventory Supervisor | G6: 67933.775 | H6: 3 | I6: 1 | J6: 2 | K6: 1 | L6: 3
A7: 1238911010 | B7: Female | C7: 34729 | D7: 42711 | F7: Marketing Coordinator | G7: 67860 | H7: 3 | I7: 2 | J7: 3 | K7: 2 | L7: 2
A8: 1238911011 | B8: Female | C8: 34051 | D8: 42958 | E8: 45662 | F8: Warehouse Receiving Associate | G8: 30030 | H8: 1 | I8: 1 | J8: 1 | K8: 2 | L8: 3
A9: 1238911012 | B9: Female | C9: 21673 | D9: 38324 | E9: 44487 | F9: Stocking Associate | G9: 27456 | H9: 2 | I9: 3 | J9: 3 | K9: 2 | L9: 2
A10: 1238911013 | B10: Female | C10: 35055 | D10: 44296 | F10: Stocking Associate | G10: 32864 | H10: 3 | I10: 2 | J10: 3 | K10: 3 | L10: 1
A11: 1238911014 | B11: Female | C11: 21784 | D11: 36400 | F11: Stocking Associate | G11: 32864 | H11: 3 | I11: 2 | J11: 3 | K11: 3 | L11: 3
A12: 1238911017 | B12: Female | C12: 21825 | D12: 33014 | E12: 45619 | F12: Stocking Associate | G12: 26520 | H12: 2 | I12: 1 | J12: 3 | K12: 3 | L12: 1
A13: 1238911020 | B13: Female | C13: 21948 | D13: 38721 | F13: Senior Category Manager | G13: 107723.2 | H13: 2 | I13: 3 | J13: 3 | K13: 2 | L13: 3
A14: 1238911021 | B14: Female | C14: 21958 | D14: 36183 | E14: 43695 | F14: Stocking Associate | G14: 27571.25 | H14: 2 | I14: 2 | J14: 1 | K14: 1 | L14: 3
A15: 1238911022 | B15: Female | C15: 28244 | D15: 39815 | F15: Stocking Associate | G15: 27571.25 | H15: 1 | I15: 2 | J15: 1 | K15: 1 | L15: 3
A16: 1238911023 | B16: Female | C16: 32709 | D16: 44571 | F16: Stocking Associate | G16: 30784 | H16: 3 | I16: 3 | J16: 3 | K16: 2 | L16: 3
A17: 1238911024 | B17: Female | C17: 22118 | D17: 37105 | F17: Stocking Associate | G17: 27300 | H17: 3 | I17: 2 | J17: 2 | K17: 2 | L17: 2
A18: 1238911025 | B18: Female | C18: 22138 | D18: 36423 | F18: Inventory Supervisor | G18: 65000 | H18: 2 | I18: 1 | J18: 2 | K18: 3 | L18: 3
A19: 1238911026 | B19: Female | C19: 22180 | D19: 37729 | F19: Inventory Retrieving Associate | G19: 28596.975 | H19: 1 | I19: 1 | J19: 3 | K19: 1 | L19: 1
A20: 1238911027 | B20: Female | C20: 22190 | D20: 40172 | F20: Manager of Operations | G20: 101936.25 | H20: 2 | I20: 2 | J20: 2 | K20: 2 | L20: 2
A21: 1238911028 | B21: Female | C21: 22293 | D21: 36294 | F21: Field App Engineer | G21: 93062.5 | H21: 1 | I21: 3 | J21: 3 | K21: 1 | L21: 1
A22: 1238911031 | B22: Female | C22: 22323 | D22: 36353 | F22: Senior Copywriter | G22: 82875 | H22: 1 | I22: 1 | J22: 2 | K22: 3 | L22: 1
A23: 1238911034 | B23: Female | C23: 22414 | D23: 37476 | F23: Inventory Retrieving Associate | G23: 28808 | H23: 2 | I23: 1 | J23: 2 | K23: 1 | L23: 2
A24: 1238911035 | B24: Female | C24: 22454 | D24: 39338 | F24: Inventory Supervisor | G24: 60797.1 | H24: 2 | I24: 3 | J24: 3 | K24: 2 | L24: 3
A25: 1238911038 | B25: Female | C25: 24539 | D25: 36294 | F25: Stocking Associate | G25: 28782 | H25: 2 | I25: 3 | J25: 3 | K25: 2 | L25: 2
A26: 1238911039 | B26: Female | C26: 22507 | D26: 37779 | F26: Inventory Retrieving Associate | G26: 30446 | H26: 2 | I26: 3 | J26: 2 | K26: 1 | L26: 1
A27: 1238911043 | B27: Female | C27: 22534 | D27: 33014 | E27: 41666 | F27: Inventory Cycle Associate | G27: 30238 | H27: 1 | I27: 2 | J27: 2 | K27: 1 | L27: 3
A28: 1238911044 | B28: Female | C28: 22709 | D28: 36498 | F28: Stocking Associate | G28: 28106 | H28: 1 | I28: 1 | J28: 3 | K28: 3 | L28: 3
A29: 1238911045 | B29: Female | C29: 22798 | D29: 36400 | F29: Stocking Associate | G29: 29510 | H29: 1 | I29: 2 | J29: 2 | K29: 3 | L29: 2
A30: 1238911046 | B30: Female | C30: 22718 | D30: 38976 | F30: Stocking Associate | G30: 30524 | H30: 3 | I30: 1 | J30: 3 | K30: 2 | L30: 3
A31: 1238911054 | B31: Female | C31: 23077 | D31: 37105 | F31: Stocking Associate | G31: 30446 | H31: 3 | I31: 3 | J31: 3 | K31: 2 | L31: 3
A32: 1238911055 | B32: Female | C32: 22465 | D32: 33014 | E32: 42422 | F32: Stocking Associate | G32: 30446 | H32: 1 | I32: 3 | J32: 2 | K32: 2 | L32: 1
A33: 1238911056 | B33: Female | C33: 23089 | D33: 44459 | E33: 45478 | F33: Stocking Associate | G33: 31616 | H33: 3 | I33: 2 | J33: 3 | K33: 2 | L33: 3
A34: 1238911059 | B34: Female | C34: 23210 | D34: 35783 | F34: Dir Content Operation | G34: 152059.7 | H34: 2 | I34: 2 | J34: 3 | K34: 2 | L34: 2
A35: 1238911060 | B35: Female | C35: 24871 | D35: 36353 | E35: 43604 | F35: Warehouse Supervisor | G35: 75337.275 | H35: 3 | I35: 1 | J35: 2 | K35: 1 | L35: 3
A36: 1238911061 | B36: Female | C36: 23215 | D36: 40386 | F36: Warehouse Supervisor | G36: 75337.275 | H36: 1 | I36: 1 | J36: 3 | K36: 1 | L36: 1
A37: 1238911066 | B37: Female | C37: 25209 | D37: 42462 | E37: 43743 | F37: Stocking Associate | G37: 27404 | H37: 1 | I37: 2 | J37: 2 | K37: 2 | L37: 1
A38: 1238911069 | B38: Female | C38: 23563 | D38: 43464 | E38: 44662 | F38: Stocking Associate | G38: 28340 | H38: 3 | I38: 1 | J38: 3 | K38: 1 | L38: 2
A39: 1238911070 | B39: Female | C39: 23598 | D39: 39668 | F39: Stocking Associate | G39: 29198 | H39: 2 | I39: 1 | J39: 3 | K39: 1 | L39: 3
A40: 1238911074 | B40: Female | C40: 23659 | D40: 36400 | F40: Stocking Associate | G40: 27300 | H40: 1 | I40: 2 | J40: 1 | K40: 2 | L40: 2
A41: 1238911075 | B41: Female | C41: 23715 | D41: 39846 | F41: Sr. VP Sales & Marketing | G41: 425199.78 | H41: 3 | I41: 2 | J41: 3 | K41: 3 | L41: 3
A42: 1238911079 | B42: Female | C42: 23930 | D42: 43840 | E42: 45169 | F42: Stocking Associate | G42: 27300 | H42: 3 | I42: 3 | J42: 3 | K42: 3 | L42: 1
A43: 1238911081 | B43: Female | C43: 23832 | D43: 36423 | F43: Supervisor | G43: 59097.675 | H43: 2 | I43: 2 | J43: 1 | K43: 2 | L43: 1
A44: 1238911082 | B44: Female | C44: 23953 | D44: 37729 | F44: Stocking Associate | G44: 31616 | H44: 3 | I44: 2 | J44: 3 | K44: 2 | L44: 2
A45: 1238911084 | B45: Female | C45: 24044 | D45: 38120 | F45: Chairman Holding | G45: 281250 | H45: 3 | I45: 2 | J45: 2 | K45: 3 | L45: 3
A46: 1238911086 | B46: Female | C46: 24072 | D46: 36353 | F46: Stocking Associate | G46: 28366 | H46: 3 | I46: 2 | J46: 3 | K46: 1 | L46: 2
A47: 1238911089 | B47: Female | C47: 24441 | D47: 39338 | F47: Repair Technician | G47: 39810 | H47: 2 | I47: 3 | J47: 1 | K47: 1 | L47: 3
A48: 1238911092 | B48: Female | C48: 24460 | D48: 44289 | E48: 45467 | F48: Stocking Associate | G48: 31460 | H48: 3 | I48: 3 | J48: 3 | K48: 1 | L48: 1
A49: 1238911093 | B49: Female | C49: 24186 | D49: 37779 | F49: Sr Mgr Project | G49: 87884.5 | H49: 2 | I49: 2 | J49: 2 | K49: 2 | L49: 2
A50: 1238911094 | B50: Female | C50: 24196 | D50: 38284 | F50: Warehouse Associate | G50: 28392 | H50: 3 | I50: 1 | J50: 3 | K50: 3 | L50: 1
A51: 1238911095 | B51: Female | C51: 34858 | D51: 43829 | F51: Warehouse Associate | G51: 28392 | H51: 2 | I51: 3 | J51: 1 | K51: 3 | L51: 1
A52: 1238911096 | B52: Female | C52: 24214 | D52: 39668 | F52: Customer Service Representative | G52: 30053.75 | H52: 1 | I52: 1 | J52: 2 | K52: 1 | L52: 2
A53: 1238911098 | B53: Female | C53: 24226 | D53: 36498 | F53: Technician IT Warehouse | G53: 58318 | H53: 1 | I53: 2 | J53: 2 | K53: 1 | L53: 1
A54: 1238911099 | B54: Female | C54: 24421 | D54: 36400 | F54: Stocking Associate | G54: 35516 | H54: 3 | I54: 3 | J54: 3 | K54: 1 | L54: 2
A55: 1238911102 | B55: Female | C55: 24284 | D55: 37904 | F55: Manager of Operations | G55: 95625.075 | H55: 3 | I55: 1 | J55: 3 | K55: 3 | L55: 2
A56: 1238911105 | B56: Female | C56: 24301 | D56: 38721 | F56: Assoc Facilities III General Agent | G56: 38077.5 | H56: 3 | I56: 3 | J56: 1 | K56: 3 | L56: 1
A57: 1238911106 | B57: Female | C57: 23162 | D57: 36294 | E57: 44797 | F57: Assoc Facilities III General Agent | G57: 38077.5 | H57: 1 | I57: 2 | J57: 1 | K57: 2 | L57: 3
A58: 1238911107 | B58: Female | C58: 24322 | D58: 38009 | F58: Shipping Supervisor | G58: 61872.5 | H58: 2 | I58: 3 | J58: 1 | K58: 1 | L58: 3
A59: 1238911108 | B59: Female | C59: 24337 | D59: 36535 | F59: Stocking Associate | G59: 31564 | H59: 3 | I59: 3 | J59: 2 | K59: 1 | L59: 1
A60: 1238911110 | B60: Female | C60: 24490 | D60: 36423 | F60: Stocking Associate | G60: 30654 | H60: 1 | I60: 3 | J60: 1 | K60: 3 | L60: 2
A61: 1238911111 | B61: Female | C61: 24511 | D61: 37729 | F61: Inventory Retrieving Associate | G61: 27664 | H61: 2 | I61: 1 | J61: 3 | K61: 2 | L61: 3
A62: 1238911112 | B62: Female | C62: 24611 | D62: 40172 | F62: Assoc Facilities I GA | G62: 31200 | H62: 2 | I62: 3 | J62: 3 | K62: 2 | L62: 2
A63: 1238911117 | B63: Female | C63: 24671 | D63: 37476 | F63: Head Wholesale | G63: 136630 | H63: 3 | I63: 2 | J63: 2 | K63: 3 | L63: 3
A64: 1238911120 | B64: Female | C64: 24732 | D64: 39788 | F64: Stocking Associate | G64: 29822 | H64: 3 | I64: 2 | J64: 3 | K64: 3 | L64: 1
A65: 1238911121 | B65: Female | C65: 24739 | D65: 39906 | E65: 44965 | F65: Assoc Facilities I GA | G65: 28862.5 | H65: 2 | I65: 3 | J65: 1 | K65: 1 | L65: 3
A66: 1238911122 | B66: Female | C66: 24778 | D66: 37779 | F66: Manager of Information Technology | G66: 137500 | H66: 3 | I66: 3 | J66: 2 | K66: 3 | L66: 2
A67: 1238911126 | B67: Female | C67: 24927 | D67: 37114 | F67: Sr Web Editor | G67: 78693.75 | H67: 3 | I67: 2 | J67: 2 | K67: 2 | L67: 2
A68: 1238911128 | B68: Female | C68: 25018 | D68: 36400 | F68: Eng Conveyor Systems | G68: 92738.75 | H68: 1 | I68: 1 | J68: 3 | K68: 3 | L68: 1
A69: 1238911135 | B69: Female | C69: 25322 | D69: 43840 | E69: 44888 | F69: Technician Maintenance | G69: 58445 | H69: 2 | I69: 1 | J69: 3 | K69: 1 | L69: 1
A70: 1238911136 | B70: Female | C70: 25487 | D70: 37105 | F70: Technician Maintenance | G70: 58445 | H70: 2 | I70: 3 | J70: 1 | K70: 3 | L70: 3
A71: 1238911137 | B71: Female | C71: 25326 | D71: 36423 | F71: Stocking Associate | G71: 31200 | H71: 3 | I71: 1 | J71: 2 | K71: 1 | L71: 2
A72: 1238911138 | B72: Female | C72: 25349 | D72: 37729 | F72: Stocking Associate | G72: 27300 | H72: 2 | I72: 2 | J72: 1 | K72: 3 | L72: 2
A73: 1238911140 | B73: Female | C73: 25247 | D73: 36294 | F73: Manager of Warehouse Operations | G73: 126250.15 | H73: 3 | I73: 3 | J73: 2 | K73: 3 | L73: 2
A74: 1238911141 | B74: Female | C74: 25382 | D74: 35783 | F74: Technician IT Warehouse | G74: 55224 | H74: 3 | I74: 1 | J74: 3 | K74: 2 | L74: 3
A75: 1238911143 | B75: Female | C75: 25415 | D75: 40386 | F75: Stocking Associate | G75: 27404 | H75: 1 | I75: 2 | J75: 1 | K75: 1 | L75: 3
A76: 1238911144 | B76: Female | C76: 25459 | D76: 37476 | F76: Warehouse Associate | G76: 31200 | H76: 1 | I76: 1 | J76: 1 | K76: 1 | L76: 2
A77: 1238911145 | B77: Female | C77: 25468 | D77: 39338 | F77: Manager of Warehouse Operations | G77: 111084.35 | H77: 3 | I77: 3 | J77: 2 | K77: 2 | L77: 2
A78: 1238911151 | B78: Female | C78: 25700 | D78: 39081 | F78: Assoc Facilities III GA | G78: 32668.75 | H78: 1 | I78: 1 | J78: 1 | K78: 2 | L78: 1
A79: 1238911153 | B79: Female | C79: 29034 | D79: 45514 | E79: 45710 | F79: Category Manager | G79: 95839.25 | H79: 3 | I79: 3 | J79: 3 | K79: 2 | L79: 3
A80: 1238911156 | B80: Female | C80: 25811 | D80: 38976 | F80: Stocking Associate | G80: 27300 | H80: 2 | I80: 1 | J80: 2 | K80: 3 | L80: 1
A81: 1238911158 | B81: Female | C81: 25839 | D81: 37904 | F81: Sr. Category Manager Mktg | G81: 117412.43 | H81: 2 | I81: 2 | J81: 2 | K81: 3 | L81: 2
A82: 1238911159 | B82: Female | C82: 25875 | D82: 40019 | F82: Stocking Associate | G82: 31200 | H82: 3 | I82: 3 | J82: 3 | K82: 2 | L82: 1
A83: 1238911160 | B83: Female | C83: 25915 | D83: 41643 | E83: 44431 | F83: Dir Sales Channel Mgmt | G83: 93253.75 | H83: 2 | I83: 1 | J83: 2 | K83: 3 | L83: 2
A84: 1238911163 | B84: Female | C84: 26031 | D84: 37105 | F84: Administrator Purchasing | G84: 62500 | H84: 1 | I84: 2 | J84: 3 | K84: 3 | L84: 1
A85: 1238911164 | B85: Female | C85: 26063 | D85: 36423 | F85: Dir Comp & Benefits HR | G85: 167968.77 | H85: 2 | I85: 2 | J85: 3 | K85: 3 | L85: 2
A86: 1238911165 | B86: Female | C86: 26131 | D86: 37729 | F86: Inventory Supervisor | G86: 63787.75 | H86: 2 | I86: 1 | J86: 2 | K86: 2 | L86: 2
A87: 1238911166 | B87: Female | C87: 26144 | D87: 40172 | F87: Inventory Supervisor | G87: 63787.75 | H87: 3 | I87: 1 | J87: 3 | K87: 2 | L87: 3
A88: 1238911168 | B88: Female | C88: 26363 | D88: 35783 | F88: Supervisor | G88: 68750 | H88: 2 | I88: 1 | J88: 1 | K88: 1 | L88: 3
A89: 1238911170 | B89: Female | C89: 26383 | D89: 40386 | F89: Dir Training & Contracts | G89: 111101.25 | H89: 3 | I89: 2 | J89: 3 | K89: 3 | L89: 2
A90: 1238911171 | B90: Female | C90: 26424 | D90: 37476 | F90: Sr Analyst Corp Business Systems | G90: 113705.7 | H90: 3 | I90: 2 | J90: 2 | K90: 2 | L90: 3
A91: 1238911172 | B91: Female | C91: 26450 | D91: 39338 | F91: Receiving Supervisor | G91: 71150.625 | H91: 2 | I91: 2 | J91: 2 | K91: 2 | L91: 2
A92: 1238911173 | B92: Female | C92: 26584 | D92: 40471 | F92: Customer Service Representative | G92: 41638.75 | H92: 3 | I92: 2 | J92: 1 | K92: 2 | L92: 3
A93: 1238911174 | B93: Female | C93: 26409 | D93: 39788 | F93: Customer Service Representative | G93: 41638.75 | H93: 3 | I93: 2 | J93: 2 | K93: 1 | L93: 3
A94: 1238911177 | B94: Female | C94: 26504 | D94: 35993 | F94: Sup Contact Cust Serv | G94: 54642.25 | H94: 1 | I94: 1 | J94: 1 | K94: 3 | L94: 2
A95: 1238911179 | B95: Female | C95: 26551 | D95: 37854 | F95: Warehouse Associate | G95: 33020 | H95: 2 | I95: 3 | J95: 1 | K95: 2 | L95: 3
... A97: 1238911181 | B97: Female | C97: 26694 | D97: 35554 | F97: Mgr Country | G97: 137812.35 | H97: 2 | I97: 3 | J97: 2 | K97: 3 | L97: 2
A98: 1238911182 | B98: Female | C98: 25256 | D98: 38678 | E98: 44723 | F98: Assoc Facilities III GA | G98: 39390 | H98: 1 | I98: 2 | J98: 1 | K98: 1 | L98: 3
A99: 1238911183 | B99: Female | C99: 26998 | D99: 38149 | F99: Facilities Assoc III | G99: 39390 | H99: 1 | I99: 2 | J99: 3 | K99: 2 | L99: 1
A100: 1238911184 | B100: Female | C100: 26726 | D100: 37417 | F100: Network Engineer | G100: 84150 | H100: 2 | I100: 1 | J100: 2 | K100: 2 | L100: 3
A101: 1238911185 | B101: Female | C101: 26870 | D101: 42178 | E101: 42643 | F101: Inventory Retrieving Associate | G101: 29354 | H101: 3 | I101: 2 | J101: 2 | K101: 2 | L101: 2
...

Sheet Male_Employees
A1: 1238911002 | B1: Male | C1: 19833 | D1: 36350 | F1: Stocking Associate | G1: 26000 | H1: 1 | I1: 3 | J1: 1 | K1: 1 | L1: 3
A2: 1238911006 | B2: Male | C2: 34706 | D2: 45441 | F2: Customer Service Help Desk | G2: 46280 | H2: 3 | I2: 2 | J2: 3 | K2: 1 | L2: 1
A3: 1238911009 | B3: Male | C3: 21283 | D3: 39668 | F3: Marketing Coordinator | G3: 67860 | H3: 3 | I3: 1 | J3: 1 | K3: 3 | L3: 3
A4: 1238911015 | B4: Male | C4: 21798 | D4: 38976 | E4: 41564 | F4: Accountant | G4: 43914 | H4: 3 | I4: 2 | J4: 2 | K4: 2 | L4: 2
A5: 1238911016 | B5: Male | C5: 31090 | D5: 41215 | E5: 43065 | F5: Accounting Associate | G5: 43914 | H5: 1 | I5: 3 | J5: 1 | K5: 2 | L5: 2
A6: 1238911018 | B6: Male | C6: 21846 | D6: 37904 | E6: 44297 | F6: Supervisor | G6: 74679.475 | H6: 3 | I6: 2 | J6: 1 | K6: 3 | L6: 1
A7: 1238911019 | B7: Male | C7: 21903 | D7: 33014 | F7: Stocking Associate | G7: 27300 | H7: 2 | I7: 3 | J7: 2 | K7: 2 | L7: 1
A8: 1238911029 | B8: Male | C8: 22295 | D8: 35783 | F8: Stocking Associate | G8: 27404 | H8: 3 | I8: 1 | J8: 3 | K8: 3 | L8: 1
A9: 1238911030 | B9: Male | C9: 36769 | D9: 45631 | F9: Stocking Associate | G9: 27404 | H9: 2 | I9: 3 | J9: 2 | K9: 2 | L9: 1
A10: 1238911032 | B10: Male | C10: 36193 | D10: 45285 | F10: Stocking Associate | G10: 27300 | H10: 1 | I10: 3 | J10: 1 | K10: 3 | L10: 3
A11: 1238911033 | B11: Male | C11: 22413 | D11: 33014 | E11: 42730 | F11: Stocking Associate | G11: 27300 | H11: 2 | I11: 2 | J11: 3 | K11: 2 | L11: 1
A12: 1238911036 | B12: Male | C12: 22482 | D12: 39788 | F12: Agent Quality Control Monitoring | G12: 48490 | H12: 2 | I12: 3 | J12: 3 | K12: 2 | L12: 3
A13: 1238911037 | B13: Male | C13: 22501 | D13: 39906 | F13: Stocking Associate | G13: 28782 | H13: 2 | I13: 2 | J13: 1 | K13: 3 | L13: 1
A14: 1238911040 | B14: Male | C14: 22513 | D14: 38284 | E14: 45539 | F14: Accountant AP | G14: 48317.5 | H14: 1 | I14: 1 | J14: 2 | K14: 2 | L14: 2
A15: 1238911041 | B15: Male | C15: 22555 | D15: 39081 | F15: Inventory Retrieving Associate | G15: 31044 | H15: 3 | I15: 3 | J15: 1 | K15: 1 | L15: 1
A16: 1238911042 | B16: Male | C16: 22532 | D16: 39668 | F16: Stocking Associate | G16: 30732 | H16: 3 | I16: 2 | J16: 3 | K16: 2 | L16: 2
A17: 1238911047 | B17: Male | C17: 22823 | D17: 39846 | F17: Customer Service Associate | G17: 35139 | H17: 1 | I17: 2 | J17: 1 | K17: 1 | L17: 3
A18: 1238911048 | B18: Male | C18: 22858 | D18: 37904 | F18: Shipping Associate | G18: 27300 | H18: 1 | I18: 2 | J18: 1 | K18: 1 | L18: 2
A19: 1238911049 | B19: Male | C19: 26991 | D19: 38664 | F19: Stocking Associate | G19: 27300 | H19: 2 | I19: 1 | J19: 3 | K19: 1 | L19: 2
A20: 1238911050 | B20: Male | C20: 22888 | D20: 40019 | F20: Stocking Associate | G20: 27664 | H20: 2 | I20: 3 | J20: 2 | K20: 1 | L20: 3
A21: 1238911051 | B21: Male | C21: 22932 | D21: 38721 | F21: Inventory Retrieving Associate | G21: 29822.5 | H21: 2 | I21: 1 | J21: 3 | K21: 2 | L21: 2
A22: 1238911052 | B22: Male | C22: 22997 | D22: 38009 | F22: Customer Service Help Desk | G22: 33800 | H22: 3 | I22: 2 | J22: 3 | K22: 2 | L22: 3
A23: 1238911053 | B23: Male | C23: 23036 | D23: 36535 | F23: Stocking Associate | G23: 31460 | H23: 3 | I23: 3 | J23: 3 | K23: 1 | L23: 2
A24: 1238911057 | B24: Male | C24: 23153 | D24: 40172 | F24: Inventory Transfer Associate | G24: 29900 | H24: 3 | I24: 3 | J24: 1 | K24: 3 | L24: 2
A25: 1238911058 | B25: Male | C25: 23012 | D25: 37729 | F25: Inventory Retrieving Associate | G25: 27404 | H25: 2 | I25: 1 | J25: 3 | K25: 3 | L25: 2
A26: 1238911062 | B26: Male | C26: 23237 | D26: 37476 | F26: Stocking Associate | G26: 27300 | H26: 2 | I26: 2 | J26: 3 | K26: 1 | L26: 3
... A30: 1238911067 | B30: Male | C30: 23468 | D30: 37779 | F30: Customer Service Associate | G30: 27569.325 | H30: 1 | I30: 1 | J30: 1 | K30: 2 | L30: 1
A31: 1238911068 | B31: Male | C31: 23493 | D31: 42667 | E31: 43382 | F31: Customer Service Associate | G31: 30706 | H31: 2 | I31: 1 | J31: 3 | K31: 2 | L31: 3
A32: 1238911071 | B32: Male | C32: 23621 | D32: 37114 | F32: Stocking Associate | G32: 26650 | H32: 3 | I32: 1 | J32: 3 | K32: 2 | L32: 1
A33: 1238911072 | B33: Male | C33: 23647 | D33: 36498 | F33: Inventory Retrieving Associate | G33: 32266 | H33: 2 | I33: 3 | J33: 1 | K33: 3 | L33: 3
A34: 1238911073 | B34: Male | C34: 23680 | D34: 44455 | E34: 45171 | F34: Inventory Retrieving Associate | G34: 32266 | H34: 3 | I34: 2 | J34: 3 | K34: 2 | L34: 2
A35: 1238911076 | B35: Male | C35: 23719 | D35: 37904 | F35: Stocking Associate | G35: 27300 | H35: 2 | I35: 3 | J35: 1 | K35: 1 | L35: 1
A36: 1238911077 | B36: Male | C36: 23732 | D36: 40019 | F36: Stocking Associate | G36: 27300 | H36: 1 | I36: 3 | J36: 1 | K36: 3 | L36: 2
A37: 1238911078 | B37: Male | C37: 23876 | D37: 38009 | E37: 45201 | F37: Manager of Operations | G37: 77809.225 | H37: 3 | I37: 3 | J37: 2 | K37: 1 | L37: 3
A38: 1238911080 | B38: Male | C38: 24076 | D38: 37105 | E38: 42146 | F38: Warehouse Supervisor | G38: 59097.675 | H38: 1 | I38: 1 | J38: 3 | K38: 1 | L38: 2
A39: 1238911083 | B39: Male | C39: 24037 | D39: 40172 | F39: Stocking Associate | G39: 28782 | H39: 1 | I39: 2 | J39: 2 | K39: 3 | L39: 2
A40: 1238911085 | B40: Male | C40: 24045 | D40: 35783 | F40: Stocking Associate | G40: 26520 | H40: 2 | I40: 3 | J40: 2 | K40: 1 | L40: 2
A41: 1238911087 | B41: Male | C41: 24086 | D41: 40386 | F41: Stocking Associate | G41: 28210 | H41: 1 | I41: 2 | J41: 2 | K41: 1 | L41: 1
A42: 1238911088 | B42: Male | C42: 24112 | D42: 43320 | E42: 44125 | F42: Inventory Retrieving Associate | G42: 27586 | H42: 3 | I42: 1 | J42: 2 | K42: 2 | L42: 2
A43: 1238911090 | B43: Male | C43: 24134 | D43: 40471 | F43: Stocking Associate | G43: 27300 | H43: 2 | I43: 3 | J43: 1 | K43: 1 | L43: 3
A44: 1238911091 | B44: Male | C44: 24175 | D44: 39788 | E44: 42067 | F44: Clerk Accounting AP | G44: 30673.75 | H44: 1 | I44: 1 | J44: 1 | K44: 1 | L44: 2
A45: 1238911097 | B45: Male | C45: 24298 | D45: 37114 | F45: Customer Service Representative | G45: 30053.75 | H45: 3 | I45: 2 | J45: 3 | K45: 1 | L45: 3
A46: 1238911100 | B46: Male | C46: 35199 | D46: 44455 | F46: Stocking Associate | G46: 29926 | H46: 3 | I46: 3 | J46: 2 | K46: 2 | L46: 3
A47: 1238911101 | B47: Male | C47: 24323 | D47: 39846 | F47: Administrator HR | G47: 66352 | H47: 1 | I47: 3 | J47: 2 | K47: 3 | L47: 3
A48: 1238911103 | B48: Male | C48: 24295 | D48: 40019 | F48: Customer Service Associate | G48: 27300 | H48: 3 | I48: 3 | J48: 2 | K48: 1 | L48: 2
A49: 1238911104 | B49: Male | C49: 32570 | D49: 42738 | F49: Customer Service Associate | G49: 27300 | H49: 3 | I49: 1 | J49: 1 | K49: 3 | L49: 2
A50: 1238911109 | B50: Male | C50: 24420 | D50: 37105 | F50: Stocking Associate | G50: 30212 | H50: 3 | I50: 1 | J50: 1 | K50: 2 | L50: 1
A51: 1238911113 | B51: Male | C51: 24550 | D51: 35783 | F51: Inventory Retrieving Associate | G51: 27768 | H51: 1 | I51: 2 | J51: 1 | K51: 1 | L51: 1
A52: 1238911114 | B52: Male | C52: 24628 | D52: 36353 | F52: Stocking Associate | G52: 26000 | H52: 1 | I52: 2 | J52: 1 | K52: 2 | L52: 1
A53: 1238911115 | B53: Male | C53: 24650 | D53: 40386 | F53: General Agent Supervisor | G53: 66969.175 | H53: 3 | I53: 1 | J53: 3 | K53: 2 | L53: 2
A54: 1238911116 | B54: Male | C54: 36045 | D54: 43780 | F54: General Agent Associate | G54: 39431.25 | H54: 3 | I54: 3 | J54: 1 | K54: 2 | L54: 2
A55: 1238911118 | B55: Male | C55: 24739 | D55: 39338 | F55: VP Customer Service | G55: 190526.05 | H55: 2 | I55: 2 | J55: 3 | K55: 2 | L55: 2
A56: 1238911119 | B56: Male | C56: 24704 | D56: 40471 | F56: Stocking Associate | G56: 27404 | H56: 3 | I56: 3 | J56: 1 | K56: 3 | L56: 3
... A58: 1238911124 | B58: Male | C58: 24890 | D58: 39081 | F58: Inventory Retrieving Associate | G58: 27300 | H58: 2 | I58: 2 | J58: 2 | K58: 3 | L58: 1
A59: 1238911125 | B59: Male | C59: 24920 | D59: 44782 | E59: 45884 | F59: Stocking Associate | G59: 27300 | H59: 3 | I59: 3 | J59: 3 | K59: 2 | L59: 3
A60: 1238911127 | B60: Male | C60: 24964 | D60: 36498 | F60: Dir Creative Marketing | G60: 174453.18 | H60: 2 | I60: 2 | J60: 2 | K60: 3 | L60: 3
A61: 1238911129 | B61: Male | C61: 25030 | D61: 38976 | E61: 44132 | F61: Customer Service Representative Help Desk | G61: 34476 | H61: 3 | I61: 2 | J61: 2 | K61: 3 | L61: 3
A62: 1238911130 | B62: Male | C62: 25154 | D62: 39846 | F62: Stocking Associate | G62: 27612 | H62: 2 | I62: 3 | J62: 3 | K62: 3 | L62: 3
A63: 1238911131 | B63: Male | C63: 25189 | D63: 37904 | F63: Stocking Associate | G63: 31668 | H63: 2 | I63: 3 | J63: 2 | K63: 3 | L63: 1
A64: 1238911132 | B64: Male | C64: 25265 | D64: 40019 | F64: Shipping Supervisor | G64: 68271.45 | H64: 2 | I64: 3 | J64: 1 | K64: 2 | L64: 2
A65: 1238911133 | B65: Male | C65: 25288 | D65: 38721 | F65: Customer Service Representative | G65: 31200 | H65: 3 | I65: 1 | J65: 1 | K65: 3 | L65: 1
A66: 1238911134 | B66: Male | C66: 25301 | D66: 38009 | F66: Stocking Associate | G66: 27066.25 | H66: 2 | I66: 1 | J66: 2 | K66: 2 | L66: 2
A67: 1238911139 | B67: Male | C67: 25362 | D67: 40172 | F67: Stocking Associate | G67: 27300 | H67: 3 | I67: 1 | J67: 3 | K67: 1 | L67: 2
A68: 1238911142 | B68: Male | C68: 23938 | D68: 43659 | E68: 44694 | F68: Stocking Associate | G68: 30550 | H68: 1 | I68: 1 | J68: 3 | K68: 1 | L68: 1
A69: 1238911146 | B69: Male | C69: 25573 | D69: 40471 | F69: Inventory Retrieving Associate | G69: 29198 | H69: 3 | I69: 2 | J69: 1 | K69: 2 | L69: 1
A70: 1238911147 | B70: Male | C70: 25643 | D70: 39788 | F70: Inventory Retrieving Associate | G70: 28080 | H70: 3 | I70: 3 | J70: 2 | K70: 3 | L70: 2
A71: 1238911148 | B71: Male | C71: 25646 | D71: 39906 | F71: Customer Service Rep Associate | G71: 27686.25 | H71: 2 | I71: 2 | J71: 3 | K71: 1 | L71: 3
A72: 1238911149 | B72: Male | C72: 25661 | D72: 37779 | F72: Customer Service Representative | G72: 30108 | H72: 1 | I72: 2 | J72: 2 | K72: 2 | L72: 2
A73: 1238911150 | B73: Male | C73: 25885 | D73: 38284 | F73: Customer Service Representative | G73: 30108 | H73: 3 | I73: 2 | J73: 2 | K73: 1 | L73: 1
A74: 1238911152 | B74: Male | C74: 25717 | D74: 39668 | F74: Customer Service Representative | G74: 31174 | H74: 3 | I74: 1 | J74: 1 | K74: 2 | L74: 1
A75: 1238911154 | B75: Male | C75: 25772 | D75: 38324 | F75: VP Admin Sales and Mktg | G75: 225205.18 | H75: 2 | I75: 2 | J75: 2 | K75: 2 | L75: 3
A76: 1238911155 | B76: Male | C76: 25800 | D76: 36400 | F76: Shipping Lead | G76: 36400 | H76: 2 | I76: 3 | J76: 2 | K76: 3 | L76: 2
A77: 1238911157 | B77: Male | C77: 25778 | D77: 39846 | F77: Stocking Associate | G77: 27872 | H77: 3 | I77: 1 | J77: 2 | K77: 3 | L77: 1
A78: 1238911161 | B78: Male | C78: 25598 | D78: 38009 | F78: Inventory Retrieving Associate | G78: 29996.25 | H78: 2 | I78: 2 | J78: 3 | K78: 2 | L78: 3
A79: 1238911162 | B79: Male | C79: 25918 | D79: 36535 | F79: Inventory Retrieving Associate | G79: 29996.25 | H79: 2 | I79: 3 | J79: 2 | K79: 1 | L79: 1
A80: 1238911167 | B80: Male | C80: 26155 | D80: 36294 | F80: Stocking Associate | G80: 27300 | H80: 1 | I80: 2 | J80: 3 | K80: 1 | L80: 1
... A83: 1238911176 | B83: Male | C83: 26473 | D83: 37779 | F83: Stocking Associate | G83: 27820 | H83: 3 | I83: 2 | J83: 1 | K83: 2 | L83: 1
A84: 1238911178 | B84: Male | C84: 32717 | D84: 45334 | E84: 45889 | F84: Account Executive Small Accounts | G84: 49997.5 | H84: 2 | I84: 3 | J84: 3 | K84: 1 | L84: 1
A85: 1238911187 | B85: Male | C85: 26749 | D85: 39815 | F85: Stocking Associate | G85: 28106 | H85: 2 | I85: 2 | J85: 3 | K85: 2 | L85: 1
A86: 1238911188 | B86: Male | C86: 26898 | D86: 39894 | F86: Stocking Associate | G86: 29224 | H86: 3 | I86: 2 | J86: 1 | K86: 1 | L86: 1
A87: 1238911189 | B87: Male | C87: 26901 | D87: 40401 | F87: Stocking Associate | G87: 27300 | H87: 1 | I87: 1 | J87: 3 | K87: 3 | L87: 2
A88: 1238911190 | B88: Male | C88: 26907 | D88: 43462 | E88: 43901 | F88: Accountant AR | G88: 41465 | H88: 1 | I88: 1 | J88: 3 | K88: 3 | L88: 3
A89: 1238911191 | B89: Male | C89: 27014 | D89: 37547 | F89: Customer Service Representative | G89: 28600 | H89: 2 | I89: 2 | J89: 1 | K89: 2 | L89: 3
A90: 1238911193 | B90: Male | C90: 27055 | D90: 36933 | F90: Inventory Retrieving Associate | G90: 27586 | H90: 1 | I90: 3 | J90: 2 | K90: 3 | L90: 3
A91: 1238911198 | B91: Male | C91: 27384 | D91: 38149 | F91: Customer Service Associate | G91: 34814 | H91: 1 | I91: 3 | J91: 1 | K91: 1 | L91: 1
A92: 1238911199 | B92: Male | C92: 27384 | D92: 37417 | F92: Customer Service Associate | G92: 34814 | H92: 2 | I92: 2 | J92: 1 | K92: 1 | L92: 2
A93: 1238911201 | B93: Male | C93: 27388 | D93: 44910 | E93: 45786 | F93: Customer Service Representative | G93: 31200 | H93: 3 | I93: 1 | J93: 2 | K93: 1 | L93: 3
A94: 1238911206 | B94: Male | C94: 27575 | D94: 44558 | E94: 45497 | F94: Account Executive Small Accounts | G94: 50000 | H94: 1 | I94: 2 | J94: 1 | K94: 2 | L94: 2
A95: 1238911209 | B95: Male | C95: 27623 | D95: 35993 | F95: Stocking Associate | G95: 29094 | H95: 3 | I95: 2 | J95: 1 | K95: 2 | L95: 1
A96: 1238911212 | B96: Male | C96: 35003 | D96: 43699 | E96: 44911 | F96: Customer Service Representative | G96: 32266 | H96: 3 | I96: 3 | J96: 2 | K96: 2 | L96: 2
A97: 1238911213 | B97: Male | C97: 27728 | D97: 39974 | F97: Sales Specialist | G97: 44642 | H97: 1 | I97: 2 | J97: 3 | K97: 3 | L97: 2
A98: 1238911214 | B98: Male | C98: 26278 | D98: 44321 | E98: 44847 | F98: Inventory Retrieving Associate | G98: 27768 | H98: 3 | I98: 3 | J98: 2 | K98: 3 | L98: 1
A99: 1238911215 | B99: Male | C99: 27750 | D99: 35755 | F99: Inventory Cycle Associate | G99: 31200 | H99: 2 | I99: 2 | J99: 3 | K99: 1 | L99: 1
A100: 1238911216 | B100: Male | C100: 27802 | D100: 38149 | F100: Customer Service Associate | G100: 30316 | H100: 1 | I100: 3 | J100: 2 | K100: 1 | L100: 3
A101: 1238911217 | B101: Male | C101: 27836 | D101: 37417 | F101: Stocking Associate | G101: 27300 | H101: 1 | I101: 1 | J101: 3 | K101: 3 | L101: 2
A102: 1238911218 | B102: Male | C102: 27869 | D102: 37065 | F102: Sr Dir Product Management | G102: 143687.5 | H102: 2 | I102: 2 | J102: 2 | K102: 3 | L102: 2
A103: 1238911219 | B103: Male | C103: 27901 | D103: 36509 | F103: Stocking Associate | G103: 30966 | H103: 1 | I103: 3 | J103: 3 | K103: 2 | L103: 2
A104: 1238911220 | B104: Male | C104: 27921 | D104: 39815 | F104: HR Business Partner | G104: 71399.9 | H104: 2 | I104: 3 | J104: 1 | K104: 2 | L104: 2
A105: 1238911223 | B105: Male | C105: 26576 | D105: 44193 | E105: 44568 | F105: Assoc Inventory Picking | G105: 31407.5 | H105: 2 | I105: 2 | J105: 2 | K105: 3 | L105: 3
A106: 1238911224 | B106: Male | C106: 28051 | D106: 38664 | F106: Customer Service Representative | G106: 28838.75 | H106: 3 | I106: 2 | J106: 1 | K106: 3 | L106: 3
...

Sheet Occupation_Pivot
A3: Row Labels | B3: Sum of EMPLOYEE_ID
A4: Stocking Associate | B4: 130085671549
A5: Inventory Retrieving Associate | B5: 45839716945
A6: Customer Service Representative | B6: 43361900630
A7: Category Manager | B7: 26017141027
A8: Merchandiser | B8: 18583673625
A9: Account Executive Small Accounts | B9: 18583671398
A10: Warehouse Associate | B10: 18583669221
A11: Agent Support Desk Customer Service | B11: 13628026690
A12: Administrator Purchasing | B12: 12389114487
A13: Engineer Application Developer | B13: 11150203615
A14: Assoc Will Call Center | B14: 11150203061
A15: Customer Service Associate | B15: 11150200231
... A310: Board Member | B310: 1238911005
A311: (blank)
A312: Grand Total | B312: 925466796378

Sheet Salary_Pivot
A3: Row Labels | B3: Max of SALARY
A4: Female | B4: 425199.78
A5: Account Executive | B5: 65625
A6: Account Executive Regional Accounts | B6: 66300
A7: Account Executive Small Accounts | B7: 50239.95
A8: Account Manager | B8: 71292.5
A9: Account Mgr Marketplace | B9: 68770
A10: Account Mgr Small Business Accounts | B10: 68750
A11: Administrative Assistant | B11: 37128
A12: Administrator Purchasing | B12: 68750
A13: Agent Public Image Customer Service | B13: 32396
A14: Agent QC Monitoring | B14: 44200
A15: Agent Support Desk Customer Service | B15: 31590
... A354: Web Designer | B354: 66912.5
A355: (blank)
A356: (blank)
A357: Grand Total | B357: 425199.78

Sheet Data_Analysis
A1: Data Analysis
A2: Salary Comparison Report
A3: Total Number of Male Employees | E3: =COUNTIF(Census!B:B,"Male") -> 321
A4: Total Number of Female Employees | E4: =COUNTIF(Census!B:B,"Female") -> 426
A5: Total Number of Employees | E5: =E3+E4 -> 747
A6: Salary Bracket
C7: Count | E7: Percentage
A8: Salary Bracket | C8: Male | D8: Female | E8: Male | F8: Female
A9: $20,000-$50,000 | C9: =COUNTIFS(Census!H:H,">=20000",Census!H:H,"<=50000", Census!B:B, "Male") -> 196 | D9: =COUNTIFS(Census!H:H,">=20000",Census!H:H,"<=50000", Census!B:B, "Female") -> 164 | E9: =C9/E5 -> 0.26238286 | F9: =D9/E5 -> 0.21954485
A10: $50,001-$100,000 | C10: =COUNTIFS(Census!H:H,">=50001",Census!H:H,"<=100000", Census!B:B, "Male") -> 110 | D10: =COUNTIFS(Census!H:H,">=50001",Census!H:H,"<=100000",Census!B:B,"Female") -> 203 | E10: =C10/E5 -> 0.14725569 | F10: =D10/E5 -> 0.27175368
A11: $100,001-200,000 | C11: =COUNTIFS(Census!H:H,">=100001",Census!H:H,"<=200000", Census!B:B, "Male") -> 13 | D11: =COUNTIFS(Census!H:H,">=100001",Census!H:H,"<=200000", Census!B:B, "Female") -> 51 | E11: =C11/E5 -> 0.017402945 | F11: =D11/E5 -> 0.068273092
A12: $200,001-300,000 | C12: =COUNTIFS(Census!H:H,">=200001",Census!H:H,"<=300000", Census!B:B, "Male") -> 2 | D12: =COUNTIFS(Census!H:H,">=200001",Census!H:H,"<=300000", Census!B:B, "Female") -> 5 | E12: =C12/E5 -> 0.0026773762 | F12: =D12/E5 -> 0.0066934404
A13: $300,001-400,000 | C13: =COUNTIFS(Census!H:H,">=300001",Census!H:H,"<=400000", Census!B:B, "Male") -> 0 | D13: =COUNTIFS(Census!H:H,">=300001",Census!H:H,"<=400000", Census!B:B, "Female") -> 2 | E13: =C13/E5 -> 0 | F13: =D13/E5 -> 0.0026773762
A14: Average Salary by Occupation
C15: Count | E15: Avg Salary
A16: Occupation | C16: Male | D16: Female | E16: Male | F16: Female
A17: Stocking Associate | C17: =COUNTIFS(Census!G:G,A17,Census!B:B,"Male") -> 60 | D17: =COUNTIFS(Census!G:G,A17,Census!B:B,"Female") -> 45 | E17: =AVERAGEIFS(Census!$H:$H,Census!$G:$G,$A17,Census!$B:$B,"Male") -> 28310.542 | F17: =AVERAGEIFS(Census!$H:$H,Census!$G:$G,$A17,Census!$B:$B,"Female") -> 29874.5
A18: Inventory Retrieving Associate | C18: =COUNTIFS(Census!G:G,A18,Census!B:B,"Male") -> 26 | D18: =COUNTIFS(Census!G:G,A18,Census!B:B,"Female") -> 11 | E18: =AVERAGEIFS(Census!$H:$H,Census!$G:$G,$A18,Census!$B:$B,"Male") -> 28510.442 | F18: =AVERAGEIFS(Census!$H:$H,Census!$G:$G,$A18,Census!$B:$B,"Female") -> 29183.543
A19: Customer Service Representative | C19: =COUNTIFS(Census!G:G,A19,Census!B:B,"Male") -> 22 | D19: =COUNTIFS(Census!G:G,A19,Census!B:B,"Female") -> 13 | E19: =AVERAGEIFS(Census!$H:$H,Census!$G:$G,$A19,Census!$B:$B,"Male") -> 30798.795 | F19: =AVERAGEIFS(Census!$H:$H,Census!$G:$G,$A19,Census!$B:$B,"Female") -> 33489.788
A20: Category Manager | C20: =COUNTIFS(Census!G:G,A20,Census!B:B,"Male") -> 6 | D20: =COUNTIFS(Census!G:G,A20,Census!B:B,"Female") -> 15 | E20: =AVERAGEIFS(Census!$H:$H,Census!$G:$G,$A20,Census!$B:$B,"Male") -> 79052.263 | F20: =AVERAGEIFS(Census!$H:$H,Census!$G:$G,$A20,Census!$B:$B,"Female") -> 82293.745
A21: Top 10 Highest Paid Positions
C22: Salary
A23: Occupation | C23: Male | D23: Female
A24: Sr. VP Sales & Marketing | C24: =SUMIFS(Census!$H:$H,Census!$G:$G,$A24,Census!$B:$B,"Male") -> 0 | D24: =SUMIFS(Census!$H:$H,Census!$G:$G,$A24,Census!$B:$B,"Female") -> 425199.78
A25: Chief Legal Officer Corporate Legal | C25: =SUMIFS(Census!$H:$H,Census!$G:$G,$A25,Census!$B:$B,"Male") -> 0 | D25: =SUMIFS(Census!$H:$H,Census!$G:$G,$A25,Census!$B:$B,"Female") -> 380842.47
A26: Sr. VP Operations | C26: =SUMIFS(Census!$H:$H,Census!$G:$G,$A26,Census!$B:$B,"Male") -> 0 | D26: =SUMIFS(Census!$H:$H,Census!$G:$G,$A26,Census!$B:$B,"Female") -> 343331.95
A27: Chairman Holding | C27: =SUMIFS(Census!$H:$H,Census!$G:$G,$A27,Census!$B:$B,"Male") -> 0 | D27: =SUMIFS(Census!$H:$H,Census!$G:$G,$A27,Census!$B:$B,"Female") -> 281250
A28: General Counsel | C28: =SUMIFS(Census!$H:$H,Census!$G:$G,$A28,Census!$B:$B,"Male") -> 0 | D28: =SUMIFS(Census!$H:$H,Census!$G:$G,$A28,Census!$B:$B,"Female") -> 262650.05
A29: CFO NA Region | C29: =SUMIFS(Census!$H:$H,Census!$G:$G,$A29,Census!$B:$B,"Male") -> 0 | D29: =SUMIFS(Census!$H:$H,Census!$G:$G,$A29,Census!$B:$B,"Female") -> 260100.1
A30: VP International | C30: =SUMIFS(Census!$H:$H,Census!$G:$G,$A30,Census!$B:$B,"Male") -> 0 | D30: =SUMIFS(Census!$H:$H,Census!$G:$G,$A30,Census!$B:$B,"Female") -> 246281.25
A31: VP Marketplace | C31: =SUMIFS(Census!$H:$H,Census!$G:$G,$A31,Census!$B:$B,"Male") -> 231875 | D31: =SUMIFS(Census!$H:$H,Census!$G:$G,$A31,Census!$B:$B,"Female") -> 0
A32: VP Admin Sales and Mktg | C32: =SUMIFS(Census!$H:$H,Census!$G:$G,$A32,Census!$B:$B,"Male") -> 225205.18 | D32: =SUMIFS(Census!$H:$H,Census!$G:$G,$A32,Census!$B:$B,"Female") -> 0
A33: Sr Dir Corporate Engineer | C33: =SUMIFS(Census!$H:$H,Census!$G:$G,$A33,Census!$B:$B,"Male") -> 0 | D33: =SUMIFS(Census!$H:$H,Census!$G:$G,$A33,Census!$B:$B,"Female") -> 221063.7
